Workbook

Sheet Service Ticket (Original)
A6: Service Ticket (Original)
A8: Customer: | B8: HAROUGE | C8: Ticket NO: | E8: 1897
A9: Field Name: | B9: GHANI
A10: Well No: | B10: VVV08-11 | C10: MKN Supervisor: | E10: M. Gomoha , Abdsalam
A11: Rig Name: | B11: ADC#27 | C11: Start Job: | E11: 46207
A12: Mileage (Km): | B12: 450 | C12: End Job: | E12: 46220
A13: Base Location: | B13: Operational Base Coordinates: Awjilah (+29.107970, +21.376782)
A14: 7'' Combination For CSG Test & Cement Job
A15: Item no. | B15: Item Description | C15: Qty | D15: Unit | E15: Unit Cost | F15: Total Cost
A16: MKN-1801 | B16: Pick-up with tools traveling to wells, per KM. | C16: =B12*2 -> 900 | D16: km (Round Trip) | E16: 3.9 | F16: =C16*E16 -> 3510
A17: MKN-1804 | B17: Supervisor or Engineer, per day or fraction | C17: 4 | D17: Day | E17: 1050 | F17: =C17*E17 -> 4200
A18: MKN-1828 | B18: Retrievable Bridg Plug Size thru 7'': First Day | C18: 1 | D18: Day | E18: 1900 | F18: =C18*E18 -> 1900
A19: MKN-1829 | B19: Retrievable Bridg Plug Size thru 7'': After First Day | C19: 13 | D19: Day | E19: 800 | F19: =C19*E19 -> 10400
A20: MKN-1808 | B20: Packer Size thru 7'': First Day | C20: 1 | D20: Day | E20: 2200 | F20: =C20*E20 -> 2200
A21: MKN-1809 | B21: Packer Size thru 7'': After First Day | C21: 3 | D21: Day | E21: 800 | F21: =C21*E21 -> 2400
A22: MKN-1963 | B22: DESERT/MARINE Surchargeadd to all invoices | D22: 0.2 | E22: =SUM(F16:F21) -> 24610 | F22: =E22*0.2 -> 4922
B24: Discount 60% | E24: =E22+F22 -> 29532 | F24: =-(E24*0.6) -> -17719.2
A40: Total = | F40: =E24+F24 -> 11812.8
A44: Customer or his agent | C44: MAKAMAN LIBYA
A49: Representative Signature | C49: Representative Signature

Sheet Service Ticket (Copy)
A6: Service Ticket (Copy)
A8: Customer: | B8: ='Service Ticket (Original)'!B8 -> HAROUGE | C8: Ticket NO: | E8: ='Service Ticket (Original)'!E8 -> 1897
A9: Field Name: | B9: ='Service Ticket (Original)'!B9 -> GHANI
A10: Well No: | B10: ='Service Ticket (Original)'!B10 -> VVV08-11 | C10: MKN Supervisor: | E10: ='Service Ticket (Original)'!E10 -> M. Gomoha , Abdsalam
A11: Rig Name: | B11: ='Service Ticket (Original)'!B11 -> ADC#27 | C11: Start Job: | E11: ='Service Ticket (Original)'!E11 -> 46207
A12: Mileage (Km): | B12: ='Service Ticket (Original)'!B12 -> 450 | C12: End Job: | E12: ='Service Ticket (Original)'!E12 -> 46220
A13: Base Location: | B13: ='Service Ticket (Original)'!B13 -> Operational Base Coordinates: Awjilah (+29.107970, +21.376782)
A14: ='Service Ticket (Original)'!A14 -> 7'' Combination For CSG Test & Cement Job
A15: Item no. | B15: Item Description | C15: Qty | D15: Unit | E15: Unit Cost | F15: Total Cost
A16: ='Service Ticket (Original)'!A16 -> MKN-1801 | B16: ='Service Ticket (Original)'!B16 -> Pick-up with tools traveling to wells, per KM. | C16: ='Service Ticket (Original)'!C16 -> 900 | D16: ='Service Ticket (Original)'!D16 -> km (Round Trip) | E16: ='Service Ticket (Original)'!E16 -> 3.9 | F16: ='Service Ticket (Original)'!F16 -> 3510
A17: ='Service Ticket (Original)'!A17 -> MKN-1804 | B17: ='Service Ticket (Original)'!B17 -> Supervisor or Engineer, per day or fraction | C17: ='Service Ticket (Original)'!C17 -> 4 | D17: ='Service Ticket (Original)'!D17 -> Day | E17: ='Service Ticket (Original)'!E17 -> 1050 | F17: ='Service Ticket (Original)'!F17 -> 4200
A18: ='Service Ticket (Original)'!A18 -> MKN-1828 | B18: ='Service Ticket (Original)'!B18 -> Retrievable Bridg Plug Size thru 7'': First Day | C18: ='Service Ticket (Original)'!C18 -> 1 | D18: ='Service Ticket (Original)'!D18 -> Day | E18: ='Service Ticket (Original)'!E18 -> 1900 | F18: ='Service Ticket (Original)'!F18 -> 1900
A19: ='Service Ticket (Original)'!A19 -> MKN-1829 | B19: ='Service Ticket (Original)'!B19 -> Retrievable Bridg Plug Size thru 7'': After First Day | C19: ='Service Ticket (Original)'!C19 -> 13 | D19: ='Service Ticket (Original)'!D19 -> Day | E19: ='Service Ticket (Original)'!E19 -> 800 | F19: ='Service Ticket (Original)'!F19 -> 10400
A20: ='Service Ticket (Original)'!A20 -> MKN-1808 | B20: ='Service Ticket (Original)'!B20 -> Packer Size thru 7'': First Day | C20: ='Service Ticket (Original)'!C20 -> 1 | D20: ='Service Ticket (Original)'!D20 -> Day | E20: ='Service Ticket (Original)'!E20 -> 2200 | F20: ='Service Ticket (Original)'!F20 -> 2200
A21: ='Service Ticket (Original)'!A21 -> MKN-1809 | B21: ='Service Ticket (Original)'!B21 -> Packer Size thru 7'': After First Day | C21: ='Service Ticket (Original)'!C21 -> 3 | D21: ='Service Ticket (Original)'!D21 -> Day | E21: ='Service Ticket (Original)'!E21 -> 800 | F21: ='Service Ticket (Original)'!F21 -> 2400
A22: ='Service Ticket (Original)'!A22 -> MKN-1963 | B22: ='Service Ticket (Original)'!B22 -> DESERT/MARINE Surchargeadd to all invoices | C22: ='Service Ticket (Original)'!C22 -> 0 | D22: ='Service Ticket (Original)'!D22 -> 0.2 | E22: ='Service Ticket (Original)'!E22 -> 24610 | F22: ='Service Ticket (Original)'!F22 -> 4922
A23: ='Service Ticket (Original)'!A23 -> 0 | B23: ='Service Ticket (Original)'!B23 -> 0 | C23: ='Service Ticket (Original)'!C23 -> 0 | D23: ='Service Ticket (Original)'!D23 -> 0 | E23: ='Service Ticket (Original)'!E23 -> 0 | F23: ='Service Ticket (Original)'!F23 -> 0
A24: ='Service Ticket (Original)'!A24 -> 0 | B24: ='Service Ticket (Original)'!B24 -> Discount 60% | C24: ='Service Ticket (Original)'!C24 -> 0 | D24: ='Service Ticket (Original)'!D24 -> 0 | E24: ='Service Ticket (Original)'!E24 -> 29532 | F24: ='Service Ticket (Original)'!F24 -> -17719.2
A25: ='Service Ticket (Original)'!A25 -> 0 | B25: ='Service Ticket (Original)'!B25 -> 0 | C25: ='Service Ticket (Original)'!C25 -> 0 | D25: ='Service Ticket (Original)'!D25 -> 0 | E25: ='Service Ticket (Original)'!E25 -> 0 | F25: ='Service Ticket (Original)'!F25 -> 0
A26: ='Service Ticket (Original)'!A26 -> 0 | B26: ='Service Ticket (Original)'!B26 -> 0 | C26: ='Service Ticket (Original)'!C26 -> 0 | D26: ='Service Ticket (Original)'!D26 -> 0 | E26: ='Service Ticket (Original)'!E26 -> 0 | F26: ='Service Ticket (Original)'!F26 -> 0
A27: ='Service Ticket (Original)'!A27 -> 0 | B27: ='Service Ticket (Original)'!B27 -> 0 | C27: ='Service Ticket (Original)'!C27 -> 0 | D27: ='Service Ticket (Original)'!D27 -> 0 | E27: ='Service Ticket (Original)'!E27 -> 0 | F27: ='Service Ticket (Original)'!F27 -> 0
... A39: ='Service Ticket (Original)'!A39 -> 0 | B39: ='Service Ticket (Original)'!B39 -> 0 | C39: ='Service Ticket (Original)'!C39 -> 0 | D39: ='Service Ticket (Original)'!D39 -> 0 | E39: ='Service Ticket (Original)'!E39 -> 0 | F39: ='Service Ticket (Original)'!F39 -> 0
A40: ='Service Ticket (Original)'!A40 -> Total = | F40: ='Service Ticket (Original)'!F40 -> 11812.8
A44: Customer or his agent | C44: MAKAMAN LIBYA
A49: Representative Signature | C49: Representative Signature

Sheet Job Log (Original)
A6: Job Log (Original) | H6: ='Service Ticket (Original)'!E8 -> 1897
F7: Ticket No:
A10: Customer: | B10: ='Service Ticket (Original)'!B8 -> HAROUGE | E10: Date: | F10: ='Service Ticket (Original)'!E12 -> 46220
A12: Field: | B12: ='Service Ticket (Original)'!B9 -> GHANI | E12: Job Type: | F12: ='Service Ticket (Original)'!A14 -> 7'' Combination For CSG Test & Cement Job
A14: Well No: | B14: ='Service Ticket (Original)'!B10 -> VVV08-11 | E14: Customer Rep. | F14: Workover Office
A16: Job Supervisor: | B16: ='Service Ticket (Original)'!E10 -> M. Gomoha , Abdsalam | E16: Rig Name: | F16: ='Service Ticket (Original)'!B11 -> ADC#27
A17: Start Job | D17: End Job | F17: Arrived To Location
A18: ='Service Ticket (Original)'!E11 -> 46207 | D18: ='Service Ticket (Original)'!E12 -> 46220 | F18: ='Service Ticket (Original)'!E11 -> 46207
A19: Date | B19: Time | C19: Pressure | D19: Total | E19: Details of the Job
A20: =A18 -> 46207 | B20: 0.47916667 | C20: - | D20: - | E20: M/Up 7''( RBP & PKR) & RIH
A21: 46208 | B21: 0.3125 | C21: - | D21: - | E21: Set 7'' RBP@5250ft,Set 7'' PKR @5200ft, P/T 500psi BTW..Good
A22: - | B22: 0.375 | C22: - | D22: - | E22: Set 7'' PKR@(5015)ft , Injectivity Test
A23: - | B23: 0.39583333 | C23: - | D23: - | E23: POOH with 7" PKR & Overshot.
A24: - | B24: - | C24: - | D24: - | E24: -
A25: - | B25: - | C25: - | D25: - | E25: Cement Job Operation.
A26: - | B26: - | C26: - | D26: - | E26: -
A27: - | B27: - | C27: - | D27: - | E27: -
A28: - | B28: - | C28: - | D28: - | E28: -
A29: 46216 | B29: 0.33333333 | C29: - | D29: - | E29: RIH 7'' PKR ,
A30: - | B30: 0.54166667 | C30: - | D30: - | E30: Set 7'' PKR @ 5008ft, P/T Good Test
A31: - | B31: 0.58333333 | C31: - | D31: - | E31: Unset 7'' PKT & POOH .
A32: 46217 | B32: - | C32: - | D32: - | E32: -
A33: - | B33: 0.29166667 | C33: - | D33: - | E33: 7'' PKR On Surface
A34: - | B34: - | C34: - | D34: - | E34: -
A35: - | B35: - | C35: - | D35: - | E35: -
A36: 46219 | B36: - | C36: - | D36: - | E36: -
A37: - | B37: 0.29166667 | C37: - | D37: - | E37: RIH 7" Overshot
A38: - | B38: 0.64583333 | C38: - | D38: - | E38: Unset 7" RBP & POOH
A39: - | B39: - | C39: - | D39: - | E39: -
A40: 46220 | B40: 0.39583333 | C40: - | D40: - | E40: RBP on surface
A41: - | B41: - | C41: - | D41: - | E41: -
A42: - | B42: - | C42: - | D42: - | E42: -
A43: - | B43: - | C43: - | D43: - | E43: -
A44: =D18 -> 46220 | B44: - | C44: - | D44: - | E44: -
A45: Customer or his agent | E45: MAKAMAN Libya
A48: Representative Signature | E48: Representative Signature

Sheet Job Log (Copy)
A6: Job Log (Copy) | H6: ='Service Ticket (Original)'!E8 -> 1897
F7: Ticket No:
A10: Customer: | B10: ='Service Ticket (Original)'!B8 -> HAROUGE | E10: Date: | F10: ='Service Ticket (Original)'!E12 -> 46220
A12: Field: | B12: ='Service Ticket (Original)'!B9 -> GHANI | E12: Job Type: | F12: ='Service Ticket (Original)'!A14 -> 7'' Combination For CSG Test & Cement Job
A14: Well No: | B14: ='Service Ticket (Original)'!B10 -> VVV08-11 | E14: Customer Rep. | F14: Workover Office
A16: Job Supervisor: | B16: ='Service Ticket (Original)'!E10 -> M. Gomoha , Abdsalam | E16: Rig Name: | F16: ='Service Ticket (Original)'!B11 -> ADC#27
A17: Start Job | D17: End Job | F17: Arrived To Location
A18: ='Service Ticket (Original)'!E11 -> 46207 | D18: ='Service Ticket (Original)'!E12 -> 46220 | F18: ='Service Ticket (Original)'!E11 -> 46207
A19: Date | B19: Time | C19: Pressure | D19: Total | E19: Details of the Job
A20: ='Job Log (Original)'!A20 -> 46207 | B20: ='Job Log (Original)'!B20 -> 0.47916667 | C20: ='Job Log (Original)'!C20 -> - | D20: ='Job Log (Original)'!D20 -> - | E20: ='Job Log (Original)'!E20 -> M/Up 7''( RBP & PKR) & RIH
A21: ='Job Log (Original)'!A21 -> 46208 | B21: ='Job Log (Original)'!B21 -> 0.3125 | C21: ='Job Log (Original)'!C21 -> - | D21: ='Job Log (Original)'!D21 -> - | E21: ='Job Log (Original)'!E21 -> Set 7'' RBP@5250ft,Set 7'' PKR @5200ft, P/T 500psi BTW..Good
A22: ='Job Log (Original)'!A22 -> - | B22: ='Job Log (Original)'!B22 -> 0.375 | C22: ='Job Log (Original)'!C22 -> - | D22: ='Job Log (Original)'!D22 -> - | E22: ='Job Log (Original)'!E22 -> Set 7'' PKR@(5015)ft , Injectivity Test
A23: ='Job Log (Original)'!A23 -> - | B23: ='Job Log (Original)'!B23 -> 0.39583333 | C23: ='Job Log (Original)'!C23 -> - | D23: ='Job Log (Original)'!D23 -> - | E23: ='Job Log (Original)'!E23 -> POOH with 7" PKR & Overshot.
A24: ='Job Log (Original)'!A24 -> - | B24: ='Job Log (Original)'!B24 -> - | C24: ='Job Log (Original)'!C24 -> - | D24: ='Job Log (Original)'!D24 -> - | E24: ='Job Log (Original)'!E24 -> -
A25: ='Job Log (Original)'!A25 -> - | B25: ='Job Log (Original)'!B25 -> - | C25: ='Job Log (Original)'!C25 -> - | D25: ='Job Log (Original)'!D25 -> - | E25: ='Job Log (Original)'!E25 -> Cement Job Operation.
A26: ='Job Log (Original)'!A26 -> - | B26: ='Job Log (Original)'!B26 -> - | C26: ='Job Log (Original)'!C26 -> - | D26: ='Job Log (Original)'!D26 -> - | E26: ='Job Log (Original)'!E26 -> -
A27: ='Job Log (Original)'!A27 -> - | B27: ='Job Log (Original)'!B27 -> - | C27: ='Job Log (Original)'!C27 -> - | D27: ='Job Log (Original)'!D27 -> - | E27: ='Job Log (Original)'!E27 -> -
A28: ='Job Log (Original)'!A28 -> - | B28: ='Job Log (Original)'!B28 -> - | C28: ='Job Log (Original)'!C28 -> - | D28: ='Job Log (Original)'!D28 -> - | E28: ='Job Log (Original)'!E28 -> -
A29: ='Job Log (Original)'!A29 -> 46216 | B29: ='Job Log (Original)'!B29 -> 0.33333333 | C29: ='Job Log (Original)'!C29 -> - | D29: ='Job Log (Original)'!D29 -> - | E29: ='Job Log (Original)'!E29 -> RIH 7'' PKR ,
A30: ='Job Log (Original)'!A30 -> - | B30: ='Job Log (Original)'!B30 -> 0.54166667 | C30: ='Job Log (Original)'!C30 -> - | D30: ='Job Log (Original)'!D30 -> - | E30: ='Job Log (Original)'!E30 -> Set 7'' PKR @ 5008ft, P/T Good Test
A31: ='Job Log (Original)'!A31 -> - | B31: ='Job Log (Original)'!B31 -> 0.58333333 | C31: ='Job Log (Original)'!C31 -> - | D31: ='Job Log (Original)'!D31 -> - | E31: ='Job Log (Original)'!E31 -> Unset 7'' PKT & POOH .
... A44: ='Job Log (Original)'!A44 -> 46220 | B44: ='Job Log (Original)'!B44 -> - | C44: ='Job Log (Original)'!C44 -> - | D44: ='Job Log (Original)'!D44 -> - | E44: ='Job Log (Original)'!E44 -> -
A45: Customer or his agent | E45: MAKAMAN Libya
A48: Representative Signature | E48: Representative Signature

Sheet WAHA 1 Price List
A1: MAKAMAN LIBYA COMPANY For Waha
A2: Official Price List
A3: Oil Service Incorporated — Tools & Testing / Special Tools Service · All prices in USD ($) · Rates per unit as noted
A4: Client: | D4: Date:
A6: A. TRANSPORTATION & PERSONNEL | F6: ← Contents
A8: Transportation & Personnel — Daily Rates
A9: Item Code | B9: Description | C9: Unit | D9: Price
A10: ='[1]1'!A7 -> MKN-001 | B10: ='[1]1'!B7 -> Pick-up with tools traveling to wells, per KM. | C10: per KM | D10: ='[1]1'!C7 -> 3
A11: ='[1]1'!A8 -> MKN-002 | B11: ='[1]1'!B8 -> Tool operator, per day or fraction | C11: per day | D11: ='[1]1'!C8 -> 950
A12: ='[1]1'!A9 -> MKN-003 | B12: ='[1]1'!B9 -> Assistant Tool Operator, per day or fraction | C12: per day | D12: ='[1]1'!C9 -> 800
A13: ='[1]1'!A10 -> MKN-004 | B13: ='[1]1'!B10 -> Supervisor or Engineer, per day or fraction | C13: per day | D13: ='[1]1'!C10 -> 1050
A14: ='[1]1'!A11 -> MKN-005 | B14: ='[1]1'!B11 -> Helper, per day or fraction | C14: per day | D14: ='[1]1'!C11 -> 500
A16: B. RETRIEVABLE PACKERS, BRIDGE PLUGS & SETTING TOOLS | F16: ← Contents
A18: Retrievable Test, Treat & Squeeze Packer
A19: Item Code | B19: Description | C19: Unit | D19: First Day | E19: Add. Day
A20: ='[1]1'!A13 -> MKN-006 | B20: Size thru 7" | C20: per day | D20: ='[1]1'!C13 -> 2200 | E20: ='[1]1'!C14 -> 850
A21: ='[1]1'!A15 -> MKN-008 | B21: Size thru 9 5/8" | C21: per day | D21: ='[1]1'!C15 -> 2900 | E21: ='[1]1'!C16 -> 950
A22: ='[1]1'!A17 -> MKN-010 | B22: Size 13 3/8" | C22: per day | D22: ='[1]1'!C17 -> 5000 | E22: ='[1]1'!C18 -> 1100
A24: Retrievable Bridge Plug — Run Separately
A25: Item Code | B25: Description | C25: Unit | D25: First Day | E25: Add. Day
A26: ='[1]1'!A21 -> MKN-012 | B26: Size thru 7" | C26: per day | D26: ='[1]1'!C21 -> 2200 | E26: ='[1]1'!C22 -> 850
A27: ='[1]1'!A23 -> MKN-014 | B27: Size thru 9 5/8" | C27: per day | D27: ='[1]1'!C23 -> 2900 | E27: ='[1]1'!C24 -> 950
A28: ='[1]1'!A25 -> MKN-016 | B28: Size 13 3/8" | C28: per day | D28: ='[1]1'!C25 -> 5000 | E28: ='[1]1'!C26 -> 1100
A30: Retrievable Bridge Plug — Run With Another MAKAMAN Packer
A31: Item Code | B31: Description | C31: Unit | D31: First Day | E31: Add. Day
A32: ='[1]1'!A29 -> MKN-018 | B32: Size thru 7" | C32: per day | D32: ='[1]1'!C29 -> 1900 | E32: ='[1]1'!C30 -> 800
A33: ='[1]1'!A31 -> MKN-020 | B33: Size thru 9 5/8" | C33: per day | D33: ='[1]1'!C31 -> 2700 | E33: ='[1]1'!C32 -> 1000
A34: ='[1]1'!A33 -> MKN-022 | B34: Size 13 3/8" | C34: per day | D34: ='[1]1'!C33 -> 4500 | E34: ='[1]1'!C34 -> 1200
A36: Setting Tools & Accessories
A37: Item Code | B37: Description | C37: Unit | D37: Price
A38: ='[1]1'!A35 -> MKN-024 | B38: ='[1]1'!B35 -> Crossover subs, Per sub, Per job. | C38: per job | D38: ='[1]1'!C35 -> 50
A39: ='[1]2'!A5 -> MKN-025 | B39: =TRIM('[1]2'!B5) -> MECHANICAL SETTING TOOL, per run | C39: per run | D39: ='[1]2'!C5 -> 1850
A40: ='[1]2'!A6 -> MKN-026 | B40: =TRIM('[1]2'!B6) -> Wire line kit for cement Retainer/Bridge plug, Per run | C40: per run | D40: ='[1]2'!C6 -> 300
A41: ='[1]2'!A7 -> MKN-027 | B41: =TRIM('[1]2'!B7) -> Tubing Stinger Coupling/ (SSA), Per job | C41: per job | D41: ='[1]2'!C7 -> 350
A42: ='[1]2'!A8 -> MKN-028 | B42: =TRIM('[1]2'!B8) -> Tubing Centralizer ,Per job | C42: per job | D42: ='[1]2'!C8 -> 300
A44: C. DRILLABLE CEMENT RETAINERS & BRIDGE PLUGS — SALES | F44: ← Contents
A46: Drillable Cement Retainers & Drillable Bridge Plug Packer — by Casing OD (Sale)
A47: Item Code | B47: Description | C47: Unit | D47: Price
A48: ='[1]2'!A14 -> MKN-029 | B48: ="Casing OD "&'[1]2'!B14 -> Casing OD 4 1/2" | C48: per unit | D48: ='[1]2'!C14 -> 3000
A49: ='[1]2'!A15 -> MKN-030 | B49: ="Casing OD "&'[1]2'!B15 -> Casing OD 5" | C49: per unit | D49: ='[1]2'!C15 -> 3200
A50: ='[1]2'!A16 -> MKN-031 | B50: ="Casing OD "&'[1]2'!B16 -> Casing OD 5 1/2" | C50: per unit | D50: ='[1]2'!C16 -> 3250
A51: ='[1]2'!A17 -> MKN-032 | B51: ="Casing OD "&'[1]2'!B17 -> Casing OD 7" | C51: per unit | D51: ='[1]2'!C17 -> 2700
A52: ='[1]2'!A18 -> MKN-033 | B52: ="Casing OD "&'[1]2'!B18 -> Casing OD 9 5/8" | C52: per unit | D52: ='[1]2'!C18 -> 4500
A53: ='[1]2'!A19 -> MKN-034 | B53: ="Casing OD "&'[1]2'!B19 -> Casing OD 13 3/8" | C53: per unit | D53: ='[1]2'!C19 -> 7200
A55: D. FISHING SUPERVISION & BASKETS | F55: ← Contents
A57: Fishing Supervision & Transport
A58: Item Code | B58: Description | C58: Unit | D58: Price
A59: ='[1]3'!A7 -> MKN 100-0205 | B59: ='[1]3'!B7 -> Fishing Tool Supervisor | C59: ='[1]3'!C7 -> $/day | D59: ='[1]3'!D7 -> 1200
A60: ='[1]3'!A8 -> MKN 100-0210 | B60: =TRIM('[1]3'!B8) -> Tools pick up | C60: ='[1]3'!C8 -> $/day | D60: ='[1]3'!D8 -> 2
A61: ='[1]3'!A9 -> MKN 100-0215 | B61: =TRIM('[1]3'!B9) -> Truck | C61: ='[1]3'!C9 -> $/1 km | D61: ='[1]3'!D9 -> 3
A63: Junk Baskets
A64: Item Code | B64: Description | C64: Unit | D64: First Day | E64: Add. Day
A65: ='[1]3'!A14 -> MKN 100-001 | B65: ='[1]3'!B14 -> Thru 3-3/4" OD | C65: $/day | D65: ='[1]3'!D14 -> 270 | E65: ='[1]3'!E14 -> 25
A66: ='[1]3'!A15 -> MKN 100-002 | B66: ='[1]3'!B15 -> Thru 4-1/4" OD | C66: $/day | D66: ='[1]3'!D15 -> 280 | E66: ='[1]3'!E15 -> 25
A67: ='[1]3'!A16 -> MKN 100-003 | B67: ='[1]3'!B16 -> Thru 4-3/4" OD | C67: $/day | D67: ='[1]3'!D16 -> 380 | E67: ='[1]3'!E16 -> 35
A68: ='[1]3'!A17 -> MKN 100-004 | B68: ='[1]3'!B17 -> Thru 5-3/4" OD | C68: $/day | D68: ='[1]3'!D17 -> 400 | E68: ='[1]3'!E17 -> 40
A69: ='[1]3'!A18 -> MKN 100-005 | B69: ='[1]3'!B18 -> Thru 6-1/8" OD | C69: $/day | D69: ='[1]3'!D18 -> 420 | E69: ='[1]3'!E18 -> 40
A70: ='[1]3'!A19 -> MKN 100-006 | B70: ='[1]3'!B19 -> Thru 6-3/4" OD | C70: $/day | D70: ='[1]3'!D19 -> 470 | E70: ='[1]3'!E19 -> 45
A71: ='[1]3'!A20 -> MKN 100-007 | B71: ='[1]3'!B20 -> Thru 7-3/4" OD | C71: $/day | D71: ='[1]3'!D20 -> 490 | E71: ='[1]3'!E20 -> 50
A72: ='[1]3'!A21 -> MKN 100-008 | B72: ='[1]3'!B21 -> Thru 9-3/4" OD | C72: $/day | D72: ='[1]3'!D21 -> 550 | E72: ='[1]3'!E21 -> 65
A73: ='[1]3'!A22 -> MKN 100-009 | B73: ='[1]3'!B22 -> Thru 10-3/4" OD | C73: $/day | D73: ='[1]3'!D22 -> 600 | E73: ='[1]3'!E22 -> 85
A74: ='[1]3'!A23 -> MKN 100-011 | B74: ='[1]3'!B23 -> Thru 12-1/4" OD | C74: $/day | D74: ='[1]3'!D23 -> 1050 | E74: ='[1]3'!E23 -> 100
A76: Reverse-Circulating Jet Baskets (Tungsten)
A77: Item Code | B77: Description | C77: Unit | D77: Price
A78: ='[1]3'!A27 -> MKN 100-012 | B78: ='[1]3'!B27 -> Thru 8-3/4" OD | C78: per run | D78: ='[1]3'!D27 -> 230
A79: ='[1]3'!A28 -> MKN 100-013 | B79: ='[1]3'!B28 -> Thru 17-1/2" OD | C79: per run | D79: ='[1]3'!D28 -> 300
A81: Junk Baskets — Poor-Boy / Drag-Tooth
A82: Item Code | B82: Description | C82: Unit | D82: Price
A83: ='[1]3'!A30 -> MKN 100-014 | B83: ='[1]3'!B30 -> Thru 7" OD | C83: per run | D83: ='[1]3'!D30 -> 510
A84: ='[1]3'!A31 -> MKN 100-015 | B84: ='[1]3'!B31 -> Thru 10-3/4" OD | C84: per run | D84: ='[1]3'!D31 -> 820
A85: ='[1]3'!A32 -> MKN 100-016 | B85: ='[1]3'!B32 -> Thru 13-3/8" OD | C85: per run | D85: ='[1]3'!D32 -> 1030
A87: Impression Blocks & Metal Boxes
A88: Item Code | B88: Description | C88: Unit | D88: Price
A89: ='[1]3'!A37 -> MKN 100-017 | B89: Impression Block — 8" OD & smaller | C89: per job | D89: ='[1]3'!D37 -> 85
A90: ='[1]3'!A38 -> MKN 100-018 | B90: Impression Block — over 8" | C90: per job | D90: ='[1]3'!D38 -> 100
A91: ='[1]3'!A40 -> MKN 100-019 | B91: Boxes, Metal — all sizes | C91: per job | D91: ='[1]3'!D40 -> 95
A93: E. WASHPIPE ACCESSORIES, BUSHINGS & CLAMPS | F93: ← Contents
A95: Washpipe Spears / Wasphip Pin
A96: Item Code | B96: Description | C96: Unit | D96: First Day | E96: Add. Day
A97: ='[1]4'!A9 -> MKN100-020 | B97: ='[1]4'!B9 -> Thru 4 1/2" Wasphip Pin | C97: $/day | D97: ='[1]4'!D9 -> 300 | E97: ='[1]4'!E9 -> 165
A98: ='[1]4'!A10 -> MKN100-021 | B98: ='[1]4'!B10 -> Thru 5 3/4" Wasphip Pin | C98: $/day | D98: ='[1]4'!D10 -> 360 | E98: ='[1]4'!E10 -> 185
A99: ='[1]4'!A11 -> MKN100-022 | B99: ='[1]4'!B11 -> Thru 8 3/8" Wasphip Pin | C99: $/day | D99: ='[1]4'!D11 -> 460 | E99: ='[1]4'!E11 -> 250
A100: ='[1]4'!A12 -> MKN100-023 | B100: ='[1]4'!B12 -> Thru 10 3/4" Wasphip Pin | C100: $/day | D100: ='[1]4'!D12 -> 490 | E100: ='[1]4'!E12 -> 265
A101: ='[1]4'!A13 -> MKN100-024 | B101: ='[1]4'!B13 -> Thru 13 3/8" Wasphip Pin | C101: $/day | D101: ='[1]4'!D13 -> 680 | E101: ='[1]4'!E13 -> 370
A102: ='[1]4'!A14 -> MKN100-025 | B102: ='[1]4'!B14 -> Thru 16 1/2" Wasphip Pin | C102: $/day | D102: ='[1]4'!D14 -> 760 | E102: ='[1]4'!E14 -> 440
A103: ='[1]4'!A15 -> MKN100-026 | B103: ='[1]4'!B15 -> Thru 20" Wasphip Pin | C103: $/day | D103: ='[1]4'!D15 -> 850 | E103: ='[1]4'!E15 -> 475
A105: Safety / Control Bushings
A106: Item Code | B106: Description | C106: Unit | D106: Price
A107: ='[1]4'!A20 -> MKN100-027 | B107: ='[1]4'!B20 -> 7 5/8" OD & Smaller | C107: per day | D107: ='[1]4'!D20 -> 165
A108: ='[1]4'!A21 -> MKN100-028 | B108: ='[1]4'!B21 -> 9 5/8" OD & Smaller | C108: per day | D108: ='[1]4'!D21 -> 260
A109: ='[1]4'!A22 -> MKN100-029 | B109: ='[1]4'!B22 -> 11 3/4" OD & Smaller | C109: per day | D109: ='[1]4'!D22 -> 300
A111: Safety Clamps — Drill Collar or Wireline
A112: Item Code | B112: Description | C112: Unit | D112: First Day | E112: Add. Day
A113: ='[1]4'!A27 -> MKN100-030 | B113: ='[1]4'!B27 -> Thru 10 segments | C113: $/day (min 4) | D113: ='[1]4'!D27 -> 150 | E113: ='[1]4'!E27 -> 15
A114: ='[1]4'!A28 -> MKN100-031 | B114: ='[1]4'!B28 -> Larger than 10 segments | C114: $/day (min 4) | D114: ='[1]4'!D28 -> 190 | E114: ='[1]4'!E28 -> 25
A116: F. CUTTERS | F116: ← Contents
A118: Inside Casing Cutters — Mechanical
A119: Item Code | B119: Description | C119: Unit | D119: Price
A120: ='[1]4'!A32 -> MKN 100-032 | B120: ='[1]4'!B32 -> Casing Thru 6-5/8" OD | C120: per cut | D120: ='[1]4'!D32 -> 1050
A121: ='[1]4'!A33 -> MKN 100-033 | B121: ='[1]4'!B33 -> Casing Thru 8-5/8" OD | C121: per cut | D121: ='[1]4'!D33 -> 1400
...

Sheet WAHA 2 Price List
A1: MAKAMAN LIBYA COMPANY For Waha
A2: Official Price List
A3: All prices in US Dollars (US$). Terms and conditions of Makaman Libya Company apply.
A4: Client: | D4: Date: | E4: =TODAY() -> 46251
A6: A. FISHING & SPECIAL TOOLS | F6: ← Contents
A8: Fishing Jar & Bumper Sub Redress Charges
A9: Item Code | B9: Description | C9: Unit | D9: Price (US$)
A10: ='[2]1'!A5 -> MKN 100-203 | B10: ='[2]1'!B5 -> Redress charge for fishing jar thru 6 ½” OD | C10: ='[2]1'!C5 -> Per run | D10: ='[2]1'!D5 -> 800
A11: ='[2]1'!A6 -> MKN 100-204 | B11: ='[2]1'!B6 -> Redress charge for fishing jar thru 8 ¾” OD | C11: ='[2]1'!C6 -> Per run | D11: ='[2]1'!D6 -> 900
A12: ='[2]1'!A7 -> MKN 100-205 | B12: ='[2]1'!B7 -> Redress charge for bumper sub thru 6 ¼” OD | C12: ='[2]1'!C7 -> Per run | D12: ='[2]1'!D7 -> 600
A13: ='[2]1'!A8 -> MKN 100-206 | B13: ='[2]1'!B8 -> Redress charge for bumper sub thru 8 ¾” OD | C13: ='[2]1'!C8 -> Per run | D13: ='[2]1'!D8 -> 700
A15: Impression Block, Junk Basket & Washover Pipe Redress
A16: Item Code | B16: Description | C16: Unit | D16: Price (US$)
A17: ='[2]1'!A12 -> MKN 100-207 | B17: ='[2]1'!B12 -> Refill impression block thru 8” OD | C17: ='[2]1'!C12 -> Per run | D17: ='[2]1'!D12 -> 910
A18: ='[2]1'!A13 -> MKN 100-208 | B18: ='[2]1'!B13 -> Refill impression block thru 13 3/8” OD | C18: ='[2]1'!C13 -> Per run | D18: ='[2]1'!D13 -> 990
A19: ='[2]1'!A14 -> MKN 100-209 | B19: ='[2]1'!B14 -> Redress junk basket with tungsten carbide thru 8 ¾” OD | C19: ='[2]1'!C14 -> Per run | D19: ='[2]1'!D14 -> 760
A20: ='[2]1'!A15 -> MKN 100-210 | B20: ='[2]1'!B15 -> Redress junk basket with tungsten carbide thru 13 3/8” OD | C20: ='[2]1'!C15 -> Per run | D20: ='[2]1'!D15 -> 885
A21: ='[2]1'!A16 -> MKN 100-211 | B21: ='[2]1'!B16 -> Redress charge for washover pipe all sizes | C21: ='[2]1'!C16 -> ….. | D21: ='[2]1'!D16 -> 2750
A23: Mills & Mill Refills
A24: Item Code | B24: Description | C24: First Day (US$) | D24: Additional Day (US$)
A25: ='[2]1'!A21 -> MKN 100-212 | B25: ='[2]1'!B21 -> Skirted mill thru 8 ¾” OD | C25: ='[2]1'!D21 -> 1350 | D25: ='[2]1'!E21 -> 500
A26: ='[2]1'!A22 -> MKN 100-213 | B26: ='[2]1'!B22 -> Skirted mill thru 13 3/8” OD | C26: ='[2]1'!D22 -> 1550 | D26: ='[2]1'!E22 -> 600
A27: ='[2]1'!A23 -> MKN 100-214 | B27: ='[2]1'!B23 -> Refill washover pipe dressed with crushed carbide for skirted mill all | C27: ='[2]1'!D23 -> 1250
A28: ='[2]1'!A24 -> MKN 100-215 | B28: ='[2]1'!B24 -> Refill junk mill with crushed carbide for skirted mill all sizes | C28: ='[2]1'!D24 -> 1350
A29: ='[2]1'!A25 -> MKN 100-216 | B29: ='[2]1'!B25 -> Flat bottom Mill all size | C29: ='[2]1'!D25 -> 385
A30: ='[2]1'!A26 -> MKN 100-217 | B30: ='[2]1'!B26 -> Refill flat bottom mill all size | C30: ='[2]1'!D26 -> 575
A32: Cable Spears, Overshot Redress Kits & Tool Inspection
A33: Item Code | B33: Description | C33: Unit | D33: Price (US$)
A34: ='[2]1'!A30 -> MKN 100-218 | B34: ='[2]1'!B30 -> Cable spear thru 8 ¾” OD | C34: ='[2]1'!C30 -> Per run | D34: ='[2]1'!D30 -> 1650
A35: ='[2]1'!A31 -> MKN 100-219 | B35: ='[2]1'!B31 -> Cable spear thru 13 3/8” OD | C35: ='[2]1'!C31 -> Per run | D35: ='[2]1'!D31 -> 1850
A36: ='[2]1'!A32 -> MKN 100-220 | B36: ='[2]1'!B32 -> Redress kit overshot wide range for all sizes | D36: ='[2]1'!D32 -> 2850
A37: ='[2]1'!A33 -> MKN 100-221 | B37: ='[2]1'!B33 -> Inspection charge for all tools as per third party company invoice | C37: ='[2]1'!C33 -> Per tool
A39: Bailers, Sand Pumps, Clamps, Elevators & Workshop Labour
A40: Item Code | B40: Description | C40: Unit | D40: First Day (US$) | E40: Additional Day (US$)
A41: ='[2]2'!A6 -> MKN 100-222 | B41: ='[2]2'!B6 -> Bailer or sand pump all sizes | C41: ='[2]2'!C6 -> Per day | D41: ='[2]2'!D6 -> 950 | E41: ='[2]2'!E6 -> 385
A42: ='[2]2'!A7 -> MKN 100-223 | B42: ='[2]2'!B7 -> Bailer or sand pump redress charge will be 50% from | C42: ='[2]2'!C7 -> 50% F.Day | D42: ='[2]2'!D7 -> 475
A43: ='[2]2'!A8 -> MKN 100-224 | B43: ='[2]2'!B8 -> Safety clamps all sizes | C43: ='[2]2'!C8 -> Per run | D43: ='[2]2'!D8 -> 40
A44: ='[2]2'!A9 -> MKN 100-225 | B44: ='[2]2'!B9 -> Elevators charge all sizes | C44: ='[2]2'!C9 -> Per day | D44: ='[2]2'!D9 -> 65
A45: ='[2]2'!A10 -> MKN 100-226 | B45: ='[2]2'!B10 -> Safety joint charge all sizes | C45: ='[2]2'!C10 -> Per run | D45: ='[2]2'!D10 -> 1850
A46: ='[2]2'!A11 -> MKN 100-227 | B46: ='[2]2'!B11 -> Workshop redressing technician rate | C46: ='[2]2'!C11 -> Per day | D46: ='[2]2'!D11 -> 750
A48: ='[2]2'!D12 -> (minimum 2days)
A50: Magnets, Grapples & Near-Bit Stabilizers
A51: Item Code | B51: Description | C51: Unit | D51: Price (US$)
A52: ='[2]2'!A15 -> MKN 100-228 | B52: ='[2]2'!B15 -> Magnet Thru 4 ½” OD | C52: ='[2]2'!C15 -> Per run | D52: ='[2]2'!D15 -> 1650
A53: ='[2]2'!A16 -> MKN 100-229 | B53: ='[2]2'!B16 -> Magnet Thru 9 ½” OD | C53: ='[2]2'!C16 -> Per run | D53: ='[2]2'!D16 -> 1850
A54: ='[2]2'!A17 -> MKN 100-230 | B54: ='[2]2'!B17 -> Magnet Type Ditch | C54: ='[2]2'!C17 -> Per day | D54: ='[2]2'!D17 -> 250
A55: ='[2]2'!A18 -> MKN 100-231 | B55: ='[2]2'!B18 -> All grapples and controls for all sizes will be charged 50% from | C55: ='[2]2'!C18 -> 50% F.Day
A56: ='[2]2'!A19 -> MKN 100-232 | B56: ='[2]2'!B19 -> Near bit stabilizer thru 7” | C56: ='[2]2'!C19 -> Per run | D56: ='[2]2'!D19 -> 2200
A57: ='[2]2'!A20 -> MKN 100-233 | B57: ='[2]2'!B20 -> Near bit stabilizer thru 9 5/8” | C57: ='[2]2'!C20 -> Per run | D57: ='[2]2'!D20 -> 2500
A59: Jar Intensifiers, Releasing Spears & Taper Mills
A60: Item Code | B60: Description | C60: Unit | D60: Price (US$)
A61: ='[2]2'!A23 -> MKN 100-234 | B61: ='[2]2'!B23 -> Jar intensifier all size per day | C61: ='[2]2'!C23 -> Per day | D61: ='[2]2'!D23 -> 750
A62: ='[2]2'!A24 -> MKN 100-235 | B62: ='[2]2'!B24 -> Releasing spear thru 7” | C62: ='[2]2'!C24 -> Per run | D62: ='[2]2'!D24 -> 1900
A63: ='[2]2'!A25 -> MKN 100-236 | B63: ='[2]2'!B25 -> Releasing Spear thru 9 5/8” | C63: ='[2]2'!C25 -> Per run | D63: ='[2]2'!D25 -> 2200
A64: ='[2]2'!A26 -> MKN 100-237 | B64: ='[2]2'!B26 -> Taper mill for thru 7” | C64: ='[2]2'!C26 -> Per day | D64: ='[2]2'!D26 -> 500
A65: ='[2]2'!A27 -> MKN 100-238 | B65: ='[2]2'!B27 -> Taper mill thru 9 5/8” | C65: ='[2]2'!C27 -> Per day | D65: ='[2]2'!D27 -> 650
A66: ='[2]2'!A28 -> MKN 100-239 | B66: ='[2]2'!B28 -> Refill taper mill for all size | C66: ='[2]2'!C28 -> Per job | D66: ='[2]2'!D28 -> 1350
A68: Technical Personnel — Daily Rates
A69: Item Code | B69: Description | C69: Unit | D69: Price (US$)
A70: ='[2]3'!A5 -> MKN 100-240 | B70: ='[2]3'!B5 -> Completion Engineer | C70: ='[2]3'!C5 -> Per Day | D70: ='[2]3'!D5 -> 1250
A71: ='[2]3'!A6 -> MKN 100-241 | B71: ='[2]3'!B6 -> Drilling Engineer | C71: ='[2]3'!C6 -> Per Day | D71: ='[2]3'!D6 -> 1300
A72: ='[2]3'!A7 -> MKN 100-242 | B72: ='[2]3'!B7 -> Work over Engineers | C72: ='[2]3'!C7 -> Per Day | D72: ='[2]3'!D7 -> 1200
A73: ='[2]3'!A8 -> MKN 100-243 | B73: ='[2]3'!B8 -> ESP completion Engineers | C73: ='[2]3'!C8 -> Per Day | D73: ='[2]3'!D8 -> 1250
A74: ='[2]3'!A9 -> MKN 100-244 | B74: ='[2]3'!B9 -> Well site Geologist | C74: ='[2]3'!C9 -> Per Day | D74: ='[2]3'!D9 -> 1300
A75: ='[2]3'!A10 -> MKN 100-245 | B75: ='[2]3'!B10 -> Open hole & cased hole DST Engineers | C75: ='[2]3'!C10 -> Per Day | D75: ='[2]3'!D10 -> 1150
A76: ='[2]3'!A11 -> MKN 100-246 | B76: ='[2]3'!B11 -> Petroleum Engineers | C76: ='[2]3'!C11 -> Per Day | D76: ='[2]3'!D11 -> 1200
A77: ='[2]3'!A12 -> MKN 100-247 | B77: ='[2]3'!B12 -> Reservoir Engineers | C77: ='[2]3'!C12 -> Per Day | D77: ='[2]3'!D12 -> 1200
A78: ='[2]3'!A13 -> MKN 100-248 | B78: ='[2]3'!B13 -> Petro physicists | C78: ='[2]3'!C13 -> Per Day | D78: ='[2]3'!D13 -> 1200
A79: ='[2]3'!A14 -> MKN 100-249 | B79: ='[2]3'!B14 -> Coring engineer | C79: ='[2]3'!C14 -> Per Day | D79: ='[2]3'!D14 -> 1100
A80: ='[2]3'!A15 -> MKN 100-250 | B80: ='[2]3'!B15 -> Logging Engineers | C80: ='[2]3'!C15 -> Per Day | D80: ='[2]3'!D15 -> 1250
A81: ='[2]3'!A16 -> MKN 100-251 | B81: ='[2]3'!B16 -> MWD Engineers | C81: ='[2]3'!C16 -> Per Day | D81: ='[2]3'!D16 -> 1400
A82: ='[2]3'!A17 -> MKN 100-252 | B82: ='[2]3'!B17 -> Company Man | C82: ='[2]3'!C17 -> Per Day | D82: ='[2]3'!D17 -> 1350
A84: Swab Cups, Machine Rental & Workshop Charges
A85: Item Code | B85: Description | C85: Unit | D85: Price (US$)
A86: ='[2]3'!A21 -> MKN 100-253 | B86: ='[2]3'!B21 -> Size 3 ½” Swab cup each | C86: ='[2]3'!C21 -> Each | D86: ='[2]3'!D21 -> 58
A87: ='[2]3'!A22 -> MKN 100-254 | B87: ='[2]3'!B22 -> Size 2 3/8” -2 7/8” swab cup each | C87: ='[2]3'!C22 -> EACH | D87: ='[2]3'!D22 -> 50
A88: ='[2]3'!A23 -> MKN 100-255 | B88: ='[2]3'!B23 -> Down hole redress charge for all size | C88: ='[2]3'!C23 -> Per Hour | D88: ='[2]3'!D23 -> 60
A89: ='[2]3'!A24 -> MKN 100-256 | B89: ='[2]3'!B24 -> Breakout Machine Rental | C89: ='[2]3'!C24 -> Per Connection | D89: ='[2]3'!D24 -> 115
A90: ='[2]3'!A25 -> MKN 100-257 | B90: ='[2]3'!B25 -> Grinding Machine | C90: ='[2]3'!C25 -> Per Hour | D90: ='[2]3'!D25 -> 200
A91: ='[2]3'!A26 -> MKN 100-258 | B91: ='[2]3'!B26 -> Pipe dope CMPD | C91: ='[2]3'!C26 -> Per Rail | D91: ='[2]3'!D26 -> 350
A92: ='[2]3'!A27 -> MKN 100-259 | B92: ='[2]3'!B27 -> Welding Machine | C92: ='[2]3'!C27 -> Per Hour | D92: ='[2]3'!D27 -> 115
A93: ='[2]3'!A28 -> MKN 100-260 | B93: ='[2]3'!B28 -> Hydraulic jar test all size | C93: ='[2]3'!C28 -> Per Test | D93: ='[2]3'!D28 -> 100
A95: B. DRILLING TOOLS & MOTORS | F95: ← Contents
A97: Drilling Jars
A98: Item Code | B98: Description | C98: Per Day (US$) | D98: Redress Charge (US$)
A99: ='[2]4'!A7 -> MKN 100-261 | B99: ='[2]4'!B7 -> Thru 4 3/4" OD | C99: ='[2]4'!C7 -> 190 | D99: ='[2]4'!D7 -> 1950
A100: ='[2]4'!A8 -> MKN 100-262 | B100: ='[2]4'!B8 -> Thru 6 1/2" OD | C100: ='[2]4'!C8 -> 220 | D100: ='[2]4'!D8 -> 2100
A101: ='[2]4'!A9 -> MKN 100-263 | B101: ='[2]4'!B9 -> Thru 8" OD | C101: ='[2]4'!C9 -> 250 | D101: ='[2]4'!D9 -> 2100
A102: ='[2]4'!A10 -> MKN 100-264 | B102: ='[2]4'!B10 -> Thru 9 1/2" OD | C102: ='[2]4'!C10 -> 260 | D102: ='[2]4'!D10 -> 2250
A104: Non-Magnetic Drill Collars
A105: Item Code | B105: Description | C105: 3-Day Minimum (US$) | D105: Each Additional Day (US$)
A106: ='[2]4'!A15 -> MKN 100-265 | B106: ='[2]4'!B15 -> Thru 6 1/2" OD | C106: ='[2]4'!C15 -> 300 | D106: ='[2]4'!D15 -> 110
A107: ='[2]4'!A16 -> MKN 100-266 | B107: ='[2]4'!B16 -> Thru 8" OD | C107: ='[2]4'!C16 -> 300 | D107: ='[2]4'!D16 -> 110
A108: ='[2]4'!A17 -> MKN 100-267 | B108: ='[2]4'!B17 -> Thru 9 1/2" OD | C108: ='[2]4'!C17 -> 300 | D108: ='[2]4'!D17 -> 110
A110: Hole Openers
A111: Item Code | B111: Description | C111: 5-Day Minimum (US$) | D111: Each Additional Day (US$)
A112: ='[2]4'!A21 -> MKN 100-268 | B112: ='[2]4'!B21 -> 12 1/4" OD | C112: ='[2]4'!C21 -> 845 | D112: ='[2]4'!D21 -> 100
A113: ='[2]4'!A22 -> MKN 100-269 | B113: ='[2]4'!B22 -> 17 1/2" OD | C113: ='[2]4'!C22 -> 1170 | D113: ='[2]4'!D22 -> 100
A114: ='[2]4'!A23 -> MKN 100-270 | B114: ='[2]4'!B23 -> 26" OD | C114: ='[2]4'!C23 -> 1470 | D114: ='[2]4'!D23 -> 100
A115: ='[2]4'!A24 -> MKN 100-271 | B115: ='[2]4'!B24 -> 36" OD | C115: ='[2]4'!C24 -> 1920 | D115: ='[2]4'!D24 -> 100
...

Sheet AGOCO Price List
A1: MAKAMAN LIBYA COMPANY For AGOCO
A2: Official Price List
A3: All prices in USD. Prices exclusive of taxes and duties. Terms and conditions per master service agreement.
A4: Client: | D4: Date:
A6: A. FISHING & SPECIAL TOOLS | F6: ← Contents
A8: Personnel & Transportation — Daily Rates
A9: Item Code | B9: Description | C9: Unit | D9: Price (USD)
A10: ='[3]5'!A7 -> MKN 100-0205 | B10: ='[3]5'!B7 -> Fishing Tool Supervisor | C10: ='[3]5'!C7 -> $/day | D10: ='[3]5'!D7 -> 1200
A11: ='[3]5'!A8 -> MKN 100-0210 | B11: ='[3]5'!B8 -> Tools pick up | C11: ='[3]5'!C8 -> $/km | D11: ='[3]5'!D8 -> 2
A12: ='[3]5'!A9 -> MKN 100-0215 | B12: ='[3]5'!B9 -> Truck | C12: ='[3]5'!C9 -> $/km | D12: ='[3]5'!D9 -> 3
A14: Baskets — Junk
A15: Item Code | B15: Description | C15: Unit | D15: First Day | E15: Additional Day
A16: ='[3]6'!A10 -> MKN 100-001 | B16: ='[3]6'!B10 -> Thru 3-3/4"OD | C16: ='[3]6'!C10 -> $/day | D16: ='[3]6'!D10 -> 270 | E16: ='[3]6'!E10 -> 25
A17: ='[3]6'!A11 -> MKN 100-002 | B17: ='[3]6'!B11 -> Thru 4-1/4"OD | C17: ='[3]6'!C11 -> $/day | D17: ='[3]6'!D11 -> 280 | E17: ='[3]6'!E11 -> 25
A18: ='[3]6'!A12 -> MKN 100-003 | B18: ='[3]6'!B12 -> Thru 4-3/4" OD | C18: ='[3]6'!C12 -> $/day | D18: ='[3]6'!D12 -> 360 | E18: ='[3]6'!E12 -> 35
A19: ='[3]6'!A13 -> MKN 100-004 | B19: ='[3]6'!B13 -> Thru 5-3/4" OD | C19: ='[3]6'!C13 -> $/day | D19: ='[3]6'!D13 -> 400 | E19: ='[3]6'!E13 -> 40
A20: ='[3]6'!A14 -> MKN 100-005 | B20: ='[3]6'!B14 -> Thru 6-1/8"OD | C20: ='[3]6'!C14 -> $/day | D20: ='[3]6'!D14 -> 420 | E20: ='[3]6'!E14 -> 40
A21: ='[3]6'!A15 -> MKN 100-006 | B21: ='[3]6'!B15 -> Thru 6-3/4"OD | C21: ='[3]6'!C15 -> $/day | D21: ='[3]6'!D15 -> 470 | E21: ='[3]6'!E15 -> 45
A22: ='[3]6'!A16 -> MKN 100-007 | B22: ='[3]6'!B16 -> Thru 7-3/4"OD | C22: ='[3]6'!C16 -> $/day | D22: ='[3]6'!D16 -> 490 | E22: ='[3]6'!E16 -> 50
A23: ='[3]6'!A17 -> MKN 100-008 | B23: ='[3]6'!B17 -> Thru 9-3/4"OD | C23: ='[3]6'!C17 -> $/day | D23: ='[3]6'!D17 -> 650 | E23: ='[3]6'!E17 -> 65
A24: ='[3]6'!A18 -> MKN 100-009 | B24: ='[3]6'!B18 -> Thru 10-3/4"OD | C24: ='[3]6'!C18 -> $/day | D24: ='[3]6'!D18 -> 800 | E24: ='[3]6'!E18 -> 85
A25: ='[3]6'!A19 -> MKN 100-011 | B25: ='[3]6'!B19 -> Thru 12-1/4"OD | C25: ='[3]6'!C19 -> $/day | D25: ='[3]6'!D19 -> 1050 | E25: ='[3]6'!E19 -> 100
A27: Baskets — Reverse Circulating Jet, Tungsten Carbide Dressed
A28: Item Code | B28: Description | C28: Unit | D28: Price (USD)
A29: ='[3]7'!A8 -> MKN 100-012 | B29: ='[3]7'!B8 -> Thru 8-3/4"OD | C29: ='[3]7'!C8 -> Price/Largest OD in/Run | D29: ='[3]7'!D8 -> 280
A30: ='[3]7'!A9 -> MKN 100-013 | B30: ='[3]7'!B9 -> Thru 17-1/2"OD | C30: ='[3]7'!C9 -> Price/Largest OD in/Run | D30: ='[3]7'!D9 -> 300
A32: Baskets — Junk (Poor Boy, Drag Tooth)
A33: Item Code | B33: Description | C33: Unit | D33: Price (USD)
A34: ='[3]7'!A11 -> MKN 100-014 | B34: ='[3]7'!B11 -> Thru 7" OD | C34: ='[3]7'!C11 -> Per Run | D34: ='[3]7'!D11 -> 510
A35: ='[3]7'!A12 -> MKN 100-015 | B35: ='[3]7'!B12 -> Thru 10-3/4"OD | C35: ='[3]7'!C12 -> Per Run | D35: ='[3]7'!D12 -> 820
A36: ='[3]7'!A13 -> MKN 100-016 | B36: ='[3]7'!B13 -> Thru 13-3/8"OD | C36: ='[3]7'!C13 -> Per Run | D36: ='[3]7'!D13 -> 1030
A38: Impression Blocks
A39: Item Code | B39: Description | C39: Unit | D39: Price (USD)
A40: ='[3]8'!A8 -> MKN 100-017 | B40: ='[3]8'!B8 -> 8" OD & Smaller | C40: ='[3]8'!C8 -> Price/Largest OD in/JOB | D40: ='[3]8'!D8 -> 85
A41: ='[3]8'!A9 -> MKN 100-018 | B41: ='[3]8'!B9 -> Over 8" | C41: ='[3]8'!C9 -> Price/Largest OD in/JOB | D41: ='[3]8'!D9 -> 100
A43: Boxes — Metal
A44: Item Code | B44: Description | C44: Unit | D44: Price (USD)
A45: ='[3]8'!A11 -> MKN 100-019 | B45: ='[3]8'!B11 -> ALL Sizes | C45: ='[3]8'!C11 -> Per Job | D45: ='[3]8'!D11 -> 95
A47: Washpipe Spears — Triple Connection or Canfield
A48: Item Code | B48: Description | C48: Unit | D48: First Day | E48: Additional Day
A49: ='[3]9'!A9 -> MKN100-020 | B49: ='[3]9'!B9 -> Thru 4 1/2" Washpipe Pin | C49: ='[3]9'!C9 -> $/day | D49: ='[3]9'!D9 -> 300 | E49: ='[3]9'!E9 -> 165
A50: ='[3]9'!A10 -> MKN100-021 | B50: ='[3]9'!B10 -> Thru 5 3/4" Washpipe Pin | C50: ='[3]9'!C10 -> $/day | D50: ='[3]9'!D10 -> 360 | E50: ='[3]9'!E10 -> 185
A51: ='[3]9'!A11 -> MKN100-022 | B51: ='[3]9'!B11 -> Thru 8 3/8" Washpipe Pin | C51: ='[3]9'!C11 -> $/day | D51: ='[3]9'!D11 -> 460 | E51: ='[3]9'!E11 -> 250
A52: ='[3]9'!A12 -> MKN100-023 | B52: ='[3]9'!B12 -> Thru 10 3/4" Washpipe Pin | C52: ='[3]9'!C12 -> $/day | D52: ='[3]9'!D12 -> 490 | E52: ='[3]9'!E12 -> 265
A53: ='[3]9'!A13 -> MKN100-024 | B53: ='[3]9'!B13 -> Thru 13 3/8" Washpipe Pin | C53: ='[3]9'!C13 -> $/day | D53: ='[3]9'!D13 -> 680 | E53: ='[3]9'!E13 -> 370
A54: ='[3]9'!A14 -> MKN100-025 | B54: ='[3]9'!B14 -> Thru 16 1/2" Washpipe Pin | C54: ='[3]9'!C14 -> $/day | D54: ='[3]9'!D14 -> 760 | E54: ='[3]9'!E14 -> 440
A55: ='[3]9'!A15 -> MKN100-026 | B55: ='[3]9'!B15 -> Thru 20" Washpipe Pin | C55: ='[3]9'!C15 -> $/day | D55: ='[3]9'!D15 -> 850 | E55: ='[3]9'!E15 -> 475
A57: Safety or Control Bushings
A58: Item Code | B58: Description | C58: Unit | D58: Price (USD)
A59: ='[3]10'!A9 -> MKN 100-027 | B59: ='[3]10'!B9 -> 7 5/8" OD & Smaller | C59: ='[3]10'!C9 -> Per Day | D59: ='[3]10'!D9 -> 165
A60: ='[3]10'!A10 -> MKN 100-028 | B60: ='[3]10'!B10 -> 9 5/8" OD & Smaller | C60: ='[3]10'!C10 -> Per Day | D60: ='[3]10'!D10 -> 260
A61: ='[3]10'!A11 -> MKN 100-029 | B61: ='[3]10'!B11 -> 11 3/4" OD & Smaller | C61: ='[3]10'!C11 -> Per Day | D61: ='[3]10'!D11 -> 300
A63: Clamps — Safety, Drill Collar
A64: Item Code | B64: Description | C64: Unit | D64: Minimum 4 Days | E64: Additional Day
A65: ='[3]11'!A10 -> MKN 100-030 | B65: ='[3]11'!B10 -> Thru 10 segments | C65: ='[3]11'!C10 -> $/day | D65: ='[3]11'!D10 -> 150 | E65: ='[3]11'!E10 -> 15
A66: ='[3]11'!A11 -> MKN 100-031 | B66: ='[3]11'!B11 -> Larger than 10 segments | C66: ='[3]11'!C11 -> $/day | D66: ='[3]11'!D11 -> 190 | E66: ='[3]11'!E11 -> 25
A68: Jars — Fishing, Hydraulic or Mechanical
A69: Item Code | B69: Description | C69: Unit | D69: First 8 Hours | E69: Additional Hour
A70: ='[3]12'!A8 -> MKN 100-045 | B70: ='[3]12'!B8 -> Thru 6-1/2" OD | C70: ='[3]12'!C8 -> Per Day | D70: ='[3]12'!D8 -> 1150 | E70: ='[3]12'!E8 -> 600
A71: ='[3]12'!A9 -> MKN 100-046 | B71: ='[3]12'!B9 -> Thru 8" OD | C71: ='[3]12'!C9 -> Per Day | D71: ='[3]12'!D9 -> 1350 | E71: ='[3]12'!E9 -> 600
A73: Jars — Bumper Sub
A74: Item Code | B74: Description | C74: Unit | D74: First 8 Hours | E74: Additional Hour
A75: ='[3]12'!A11 -> MKN 100-047 | B75: ='[3]12'!B11 -> 4-1/4" OD | C75: ='[3]12'!C11 -> Per Day | D75: ='[3]12'!D11 -> 400 | E75: ='[3]12'!E11 -> 240
A76: ='[3]12'!A12 -> MKN 100-048 | B76: ='[3]12'!B12 -> 6-1/4" OD | C76: ='[3]12'!C12 -> Per Day | D76: ='[3]12'!D12 -> 680 | E76: ='[3]12'!E12 -> 330
A78: Mills — Dressed with Tungsten Carbide
A79: Item Code | B79: Description | C79: Unit | D79: First 30 ft | E79: Additional Day
A80: ='[3]13'!A8 -> MKN 100-058 | B80: ='[3]13'!B8 -> Thru 10 3/4"OD | C80: ='[3]13'!C8 -> Per Tool | D80: ='[3]13'!D8 -> 7500 | E80: ='[3]13'!E8 -> 55
A81: ='[3]13'!A9 -> MKN 100-059 | B81: ='[3]13'!B9 -> Thru 13 3/8"OD | C81: ='[3]13'!C9 -> Per Tool | D81: ='[3]13'!D9 -> 8150 | E81: ='[3]13'!E9 -> 70
A83: Milling Sections
A84: Item Code | B84: Description | C84: Unit | D84: First 30 ft | E84: Additional Day
A85: ='[3]13'!A11 -> MKN 100-060 | B85: ='[3]13'!B11 -> Thru 8 5/8"OD | C85: ='[3]13'!C11 -> Per Tool | D85: ='[3]13'!D11 -> 5300 | E85: ='[3]13'!E11 -> 100
A86: ='[3]13'!A12 -> MKN 100-061 | B86: ='[3]13'!B12 -> Thru 10 3/4"OD | C86: ='[3]13'!C12 -> Per Tool | D86: ='[3]13'!D12 -> 6400 | E86: ='[3]13'!E12 -> 130
A87: ='[3]13'!A13 -> MKN 100-062 | B87: ='[3]13'!B13 -> Thru 13 3/8"OD | C87: ='[3]13'!C13 -> Per Tool | D87: ='[3]13'!D13 -> 8300 | E87: ='[3]13'!E13 -> 140
A88: ='[3]13'!A14 -> MKN 100-063 | B88: ='[3]13'!B14 -> Thru 20"OD | C88: ='[3]13'!C14 -> Per Tool | D88: ='[3]13'!D14 -> 12350 | E88: ='[3]13'!E14 -> 265
A90: Mills — Cement, Junk or Bladed
A91: Item Code | B91: Description | C91: Unit | D91: Price (USD)
A92: ='[3]14'!A7 -> MKN 100-064 | B92: ='[3]14'!B7 -> ALL Sizes | C92: ='[3]14'!C6 -> PER RUN | D92: ='[3]14'!D6 -> 600
A94: Mills — Cement, Concave or Flat Bottom
A95: Item Code | B95: Description | C95: Unit | D95: Price (USD)
A96: ='[3]14'!A10 -> MKN 100-065 | B96: ='[3]14'!B10 -> Thru 12"OD | C96: ='[3]14'!C10 -> PER RUN | D96: ='[3]14'!D10 -> 310
A97: ='[3]14'!A11 -> MKN 100-066 | B97: ='[3]14'!B11 -> Thru 15"OD | C97: ='[3]14'!C11 -> PER RUN | D97: ='[3]14'!D11 -> 350
A98: ='[3]14'!A12 -> MKN 100-067 | B98: ='[3]14'!B12 -> Thru 20"OD | C98: ='[3]14'!C12 -> PER RUN | D98: ='[3]14'!D12 -> 350
A99: ='[3]14'!A13 -> MKN 100-068 | B99: ='[3]14'!B13 -> Thru 24"OD | C99: ='[3]14'!C13 -> PER RUN | D99: ='[3]14'!D13 -> 510
A100: ='[3]14'!A14 -> MKN 100-069 | B100: ='[3]14'!B14 -> Thru 26"OD | C100: ='[3]14'!C14 -> PER RUN | D100: ='[3]14'!D14 -> 510
A102: Mills — Packer, Pilot or Tapered
A103: Item Code | B103: Description | C103: Unit | D103: Price (USD)
A104: ='[3]14'!A16 -> MKN 100-070 | B104: ='[3]14'!B16 -> Thru 15"OD | C104: ='[3]14'!C16 -> PER RUN | D104: ='[3]14'!D16 -> 420
A105: ='[3]14'!A17 -> MKN 100-071 | B105: ='[3]14'!B17 -> Thru 20"OD | C105: ='[3]14'!C17 -> PER RUN | D105: ='[3]14'!D17 -> 460
A106: ='[3]14'!A18 -> MKN 100-072 | B106: ='[3]14'!B18 -> Thru 24"OD | C106: ='[3]14'!C18 -> PER RUN | D106: ='[3]14'!D18 -> 650
A107: ='[3]14'!A19 -> MKN 100-073 | B107: ='[3]14'!B19 -> Thru 26"OD | C107: ='[3]14'!C19 -> PER RUN | D107: ='[3]14'!D19 -> 670
A108: ='[3]14'!A20 -> MKN 100-074 | B108: ='[3]14'!B20 -> Thru 30"OD | C108: ='[3]14'!C20 -> PER RUN | D108: ='[3]14'!D20 -> 810
A110: Overshots — Series 150 Rotary
A111: Item Code | B111: Description | C111: Unit | D111: First Day | E111: Additional Day
A112: ='[3]15'!A9 -> MKN 100-075 | B112: ='[3]15'!B9 -> Thru 4-1/8"OD | C112: ='[3]15'!C9 -> S/day | D112: ='[3]15'!E9 -> 500 | E112: ='[3]15'!F9 -> 200
A113: ='[3]15'!A10 -> MKN 100-076 | B113: ='[3]15'!B10 -> Thru 5-3/8"OD | C113: ='[3]15'!C10 -> S/day | D113: ='[3]15'!E10 -> 570 | E113: ='[3]15'!F10 -> 220
A114: ='[3]15'!A11 -> MKN 100-077 | B114: ='[3]15'!B11 -> Thru 8-7/8"OD | C114: ='[3]15'!C11 -> S/day | D114: ='[3]15'!E11 -> 800 | E114: ='[3]15'!F11 -> 330
A115: ='[3]15'!A12 -> MKN 100-078 | B115: ='[3]15'!B12 -> Thru 11-3/4"OD | C115: ='[3]15'!C12 -> S/day | D115: ='[3]15'!E12 -> 1150 | E115: ='[3]15'!F12 -> 585
A117: Overshots — Series 70 Short Catch
A118: Item Code | B118: Description | C118: Unit | D118: First Day | E118: Additional Day
A119: ='[3]16'!A9 -> MKN 100-079 | B119: ='[3]16'!B9 -> Thru 4 3/4"OD | C119: ='[3]16'!C9 -> $/day | D119: ='[3]16'!D9 -> 800 | E119: ='[3]16'!E9 -> 310
...

Sheet HOO Price List
A1: MAKAMAN LIBYA COMPANY For Harouge Oil Operations
A2: Official Price List — Tools and Testing
A3: All prices in USD ($). Prices subject to surcharges per Terms & Conditions. Quotation only — not a contract.
A4: Client: | D4: Date:
A6: A. TOOLS SERVICES | F6: ← Contents
A8: Transportation & Personnel
A9: Item Code | B9: Description | C9: Price
A10: ='[4]1'!A11 -> MKN-1801 | B10: ='[4]1'!B11 -> Pick-up with tools traveling to wells, per KM. | C10: ='[4]1'!C11 -> 3.9
A11: ='[4]1'!A12 -> MKN-1802 | B11: ='[4]1'!B12 -> Tool operator, per day or fraction | C11: ='[4]1'!C12 -> 950
A12: ='[4]1'!A13 -> MKN-1803 | B12: ='[4]1'!B13 -> Assistant Tool Operator, per day or fraction | C12: ='[4]1'!C13 -> 800
A13: ='[4]1'!A14 -> MKN-1804 | B13: ='[4]1'!B14 -> Supervisor or Engineer, per day or fraction | C13: ='[4]1'!C14 -> 1050
A14: ='[4]1'!A15 -> MKN-1805 | B14: ='[4]1'!B15 -> Helper, per day or fraction | C14: ='[4]1'!C15 -> 500
A15: ='[4]1'!A16 -> MKN-1806 | B15: ='[4]1'!B16 -> STAND-BY FRIST SIX HOURS after arriving on location | C15: ='[4]1'!C16 -> No charge
B16: ='[4]1'!B17 -> After the Frist Six 06) Hours, STAND-BY, PER HOUR OR FRACTION until job started per tool, until PERSONNEL CHARGES will be in addition. | C16: ='[4]1'!C17 -> 90
A17: ='[4]1'!A18 -> MKN-1807 | B17: ='[4]1'!B18 -> JOB CANCELITION When called to location and the job is not run, | C17: ='[4]1'!C18 -> 1800
A18: Job cancellation: when called to location and the job is not run due to circumstances beyond our control, personnel charges are in addition.
A20: Retrievable Test, Treat & Squeeze Packer — First 8 Hours or Fraction
A21: Item Code | B21: Description | C21: Price
A22: ='[4]1'!A26 -> MKN-1808 | B22: ='[4]1'!B26 -> "Size thru 7 | C22: ='[4]1'!C26 -> 2200
A23: ='[4]1'!A27 -> MKN-1809 | B23: ='[4]1'!B27 -> AFTER FIRST DAY size 7" | C23: ='[4]1'!C27 -> 800
A24: ='[4]1'!A28 -> MKN-1810 | B24: ='[4]1'!B28 -> "Size thru 95/8. | C24: ='[4]1'!C28 -> 2900
A25: ='[4]1'!A29 -> MKN-1811 | B25: ='[4]1'!B29 -> AFTER FIRST DAY size 9 5/8" | C25: ='[4]1'!C29 -> 950
A26: ='[4]1'!A30 -> MKN-1812 | B26: ='[4]1'!B30 -> "Size 13 3/8. | C26: ='[4]1'!C30 -> 5000
A27: ='[4]1'!A31 -> MKN-1813 | B27: ='[4]1'!B31 -> AFTER FIRST DAY size 13 3/8" | C27: ='[4]1'!C31 -> 1100
A28: ='[4]1'!A32 -> MKN-1814 | B28: ='[4]1'!B32 -> All sizes, above 15,000 ft. per 100 ft. or fraction add | C28: ='[4]1'!C32 -> 75
A29: ='[4]1'!A33 -> MKN-1815 | B29: ='[4]1'!B33 -> ADDITIONAL ZONE. Each ADDITIONAL ZONE on same run in well, any depth: | C29: ='[4]1'!C33 -> 800
A30: ='[4]1'!A36 -> MKN-1816 | B30: ='[4]1'!B36 -> Unsuccessful run. | C30: ='[4]1'!C36 -> 1100
A31: ='[4]1'!A37 -> MKN-1817 | B31: ='[4]1'!B37 -> Each Reset Packer For All Sizes | C31: ='[4]1'!C37 -> 200
A32: Price is determined by size and depth packer set. Job time begins when the tool starts in the well and ends when recovered. Additional zone charge applies when the tool is moved to another zone for any purpose (excludes looking for casing leaks).
A34: Retrievable Bridge Plug (run with another Makaman packer) — First 8 Hours or Fraction
A35: Item Code | B35: Description | C35: Price
A36: ='[4]2'!A10 -> MKN-1818 | B36: ='[4]2'!B10 -> Size thru 7" : first day | C36: ='[4]2'!C10 -> 2200
A37: ='[4]2'!A11 -> MKN-1819 | B37: ='[4]2'!B11 -> Size thru 7" : after first day | C37: ='[4]2'!C11 -> 850
A38: ='[4]2'!A12 -> MKN-1820 | B38: ='[4]2'!B12 -> Size thru 9 5/8" : first day | C38: ='[4]2'!C12 -> 2900
A39: ='[4]2'!A13 -> MKN-1821 | B39: ='[4]2'!B13 -> Size thru 9 5/8" : after first day | C39: ='[4]2'!C13 -> 950
A40: ='[4]2'!A14 -> MKN-1822 | B40: ='[4]2'!B14 -> Size 13 3/8" : first day | C40: ='[4]2'!C14 -> 5000
A41: ='[4]2'!A15 -> MKN-1823 | B41: ='[4]2'!B15 -> Size 13 3/8" : after first day | C41: ='[4]2'!C15 -> 1100
A42: ='[4]2'!A16 -> MKN-1824 | B42: ='[4]2'!B16 -> All sizes above 15,000 ft. per 100 ft. or fraction: add | C42: ='[4]2'!C16 -> 75
A43: ='[4]2'!A17 -> MKN-1825 | B43: ='[4]2'!B17 -> ADDITIONAL TIME. Each additional consecutive 8-hour or fraction | C43: ='[4]2'!C17 -> 1100
A44: ='[4]2'!A18 -> MKN-1826 | B44: ='[4]2'!B18 -> Frac sand (M.E.) 20–40 per pound | C44: ='[4]2'!C18 -> 3.6
A45: ='[4]2'!A19 -> MKN-1827 | B45: ='[4]2'!B19 -> Unsuccessful run | C45: ='[4]2'!C19 -> 1100
A47: Retrievable Bridge Plug (run separately) — First 8 Hours or Fraction
A48: Item Code | B48: Description | C48: Price
A49: ='[4]2'!A27 -> MKN-1828 | B49: ='[4]2'!B27 -> Size thru 7" : first day | C49: ='[4]2'!C27 -> 1900
A50: ='[4]2'!A28 -> MKN-1829 | B50: ='[4]2'!B28 -> Size thru 7" : after first day | C50: ='[4]2'!C28 -> 800
A51: ='[4]2'!A29 -> MKN-1830 | B51: ='[4]2'!B29 -> Size thru 9 5/8" : first day | C51: ='[4]2'!C29 -> 2700
A52: ='[4]2'!A30 -> MKN-1831 | B52: ='[4]2'!B30 -> Size thru 9 5/8" : after first day | C52: ='[4]2'!C30 -> 1000
A53: ='[4]2'!A31 -> MKN-1832 | B53: ='[4]2'!B31 -> Size 13 3/8" : first day | C53: ='[4]2'!C31 -> 4500
A54: ='[4]2'!A32 -> MKN-1833 | B54: ='[4]2'!B32 -> Size 13 3/8" : after first day | C54: ='[4]2'!C32 -> 1200
A55: ='[4]2'!A33 -> MKN-1834 | B55: ='[4]2'!B33 -> All sizes above 15,000 ft. per 100 ft. or fraction: add | C55: ='[4]2'!C33 -> 70
A56: ='[4]2'!A34 -> MKN-1835 | B56: ='[4]2'!B34 -> ADDITIONAL TIME. Each additional consecutive 8-hour or fraction | C56: ='[4]2'!C34 -> 800
A57: ='[4]2'!A35 -> MKN-1836 | B57: ='[4]2'!B35 -> Each reset on ADDITIONAL ZONE | C57: ='[4]2'!C35 -> 700
A58: ='[4]2'!A36 -> MKN-1837 | B58: ='[4]2'!B36 -> Unsuccessful run | C58: ='[4]2'!C36 -> 1300
A59: ='[4]2'!A37 -> MKN-1838 | B59: ='[4]2'!B37 -> Crossover subs, per sub, per job | C59: ='[4]2'!C37 -> 50
A61: Drill Cement Retainers & Drillable Bridge Plug — Special Tools Service
A62: Item Code | B62: Description | C62: Price
A63: ='[4]3'!A15 -> MKN-1839 | B63: ='[4]3'!B15 -> MECHANICAL SETTING TOOL, per run | C63: ='[4]3'!C15 -> 2500
A64: ='[4]3'!A16 -> MKN-1840 | B64: ='[4]3'!B16 -> Wire line kit for cement Retainer/Bridge plug, Per run | C64: ='[4]3'!C16 -> 300
A65: ='[4]3'!A17 -> MKN-1841 | B65: ='[4]3'!B17 -> Tubing Stinger Coupling/ (SSA), Per job | C65: ='[4]3'!C17 -> 600
A66: ='[4]3'!A18 -> MKN-1842 | B66: ='[4]3'!B18 -> Tubing Centralizer ,Per job | C66: ='[4]3'!C18 -> 300
A68: Sales — per Casing OD
A69: Item Code | B69: Description | C69: Price
A70: ='[4]3'!A23 -> MKN-1843 | B70: ='[4]3'!B23 -> 4 1/2" | C70: ='[4]3'!C23 -> 3500
A71: ='[4]3'!A24 -> MKN-1844 | B71: ='[4]3'!B24 -> 5" | C71: ='[4]3'!C24 -> 3560
A72: ='[4]3'!A25 -> MKN-1845 | B72: ='[4]3'!B25 -> 5 1/2" | C72: ='[4]3'!C25 -> 3560
A73: ='[4]3'!A26 -> MKN-1846 | B73: ='[4]3'!B26 -> 7" | C73: ='[4]3'!C26 -> 3900
A74: ='[4]3'!A27 -> MKN-1847 | B74: ='[4]3'!B27 -> 9 5/8" | C74: ='[4]3'!C27 -> 5200
A75: ='[4]3'!A28 -> MKN-1848 | B75: ='[4]3'!B28 -> 13 3/8" | C75: ='[4]3'!C28 -> 8200
A77: B. DRILLING TOOLS & FILTRATION | F77: ← Contents
A79: Drilling Tools — Stabilizers, Jars & Casing Scrapers
A80: Item Code | B80: Description | C80: Per Day | D80: Add. Day | E80: Stand-By
A81: ='[4]4'!A7 -> MKN-1849 | B81: ='[4]4'!B7 -> STABILIZER Thru 6 1/8" | C81: ='[4]4'!C7 -> 534 | D81: ='[4]4'!D7 -> 200 | E81: ='[4]4'!E7 -> 110
A82: ='[4]4'!A8 -> MKN-1850 | B82: ='[4]4'!B8 -> STABILIZER Thru 8 5/8" | C82: ='[4]4'!C8 -> 607 | D82: ='[4]4'!D8 -> 250 | E82: ='[4]4'!E8 -> 122
A83: ='[4]4'!A9 -> MKN-1851 | B83: ='[4]4'!B9 -> STABILIZER Thru 12 1/4" | C83: ='[4]4'!C9 -> 662 | D83: ='[4]4'!D9 -> 300 | E83: ='[4]4'!E9 -> 133
A84: ='[4]4'!A10 -> MKN-1852 | B84: ='[4]4'!B10 -> STABILIZER Thru 17 1/2" | C84: ='[4]4'!C10 -> 772 | D84: ='[4]4'!D10 -> 350 | E84: ='[4]4'!E10 -> 166
A85: ='[4]4'!A11 -> MKN-1853 | B85: ='[4]4'!B11 -> HYDROLIC DRILLING JAR 4 3/4" OD & UNDER | C85: ='[4]4'!C11 -> 1150 | D85: ='[4]4'!D11 -> 900 | E85: ='[4]4'!E11 -> 265
A86: ='[4]4'!A12 -> MKN-1854 | B86: ='[4]4'!B12 -> HYDROLIC DRILLING JAR THRU 5 3/4" OD | C86: ='[4]4'!C12 -> 1600 | D86: ='[4]4'!D12 -> 1000 | E86: ='[4]4'!E12 -> 420
A87: ='[4]4'!A13 -> MKN-1855 | B87: ='[4]4'!B13 -> HYDROLIC DRILLING JAR THRU 6 1/4" OD | C87: ='[4]4'!C13 -> 1800 | D87: ='[4]4'!D13 -> 1200 | E87: ='[4]4'!E13 -> 450
A88: ='[4]4'!A14 -> MKN-1856 | B88: ='[4]4'!B14 -> HYDROLIC DRILLING JAR THRU 7 3/4" OD | C88: ='[4]4'!C14 -> 2000 | D88: ='[4]4'!D14 -> 1300 | E88: ='[4]4'!E14 -> 520
A89: ='[4]4'!A15 -> MKN-1857 | B89: ='[4]4'!B15 -> CASING SCRAPER 5" & 5 1/2" | C89: ='[4]4'!C15 -> 400 | D89: ='[4]4'!D15 -> 200 | E89: ='[4]4'!E15 -> 120
A90: ='[4]4'!A16 -> MKN-1858 | B90: ='[4]4'!B16 -> CASING SCRAPER 7" | C90: ='[4]4'!C16 -> 450 | D90: ='[4]4'!D16 -> 220 | E90: ='[4]4'!E16 -> 140
A91: ='[4]4'!A17 -> MKN-1859 | B91: ='[4]4'!B17 -> CASING SCRAPER 9 5/8" | C91: ='[4]4'!C17 -> 550 | D91: ='[4]4'!D17 -> 250 | E91: ='[4]4'!E17 -> 160
A93: Filtration Services
A94: Item Code | B94: Description | C94: Unit | D94: Price
A95: ='[4]5'!A6 -> MKN-1860 | B95: ='[4]5'!B6 -> SERVICE SUPERVISOR FILTRATION UNIT | C95: ='[4]5'!C6 -> PER DAY | D95: ='[4]5'!D6 -> 1000
A96: ='[4]5'!A7 -> MKN-1861 | B96: ='[4]5'!B7 -> HELPER | C96: ='[4]5'!C7 -> PER DAY | D96: ='[4]5'!D7 -> 500
A97: ='[4]5'!A8 -> MKN-1862 | B97: ='[4]5'!B8 -> FILTRATION UNIT AND C-PUMP TRANSPORT | C97: ='[4]5'!C8 -> PER DAY | D97: ='[4]5'!D8 -> 400
A98: ='[4]5'!A9 -> MKN-1863 | B98: ='[4]5'!B9 -> FRAC TANK | C98: ='[4]5'!C9 -> PER JOB | D98: ='[4]5'!D9 -> 900
A99: ='[4]5'!A10 -> MKN-1864 | B99: ='[4]5'!B10 -> CENTER FUGAL PUMP | C99: ='[4]5'!C10 -> PER JOB | D99: ='[4]5'!D10 -> 900
A100: ='[4]5'!A11 -> MKN-1865 | B100: ='[4]5'!B11 -> FILTRATION UNIT | C100: ='[4]5'!C11 -> PER DAY | D100: ='[4]5'!D11 -> 300
A101: ='[4]5'!A12 -> MKN-1866 | B101: ='[4]5'!B12 -> FILTRATION CATRIDGES | C101: ='[4]5'!C12 -> PER EACH | D101: ='[4]5'!D12 -> 20
A103: C. PUMPING & STIMULATION SERVICES | F103: ← Contents
A105: 500 HP Pump
A106: Item Code | B106: Description | C106: Unit | D106: Price
A107: ='[4]6'!A6 -> MKN-1867 | B107: ='[4]6'!B6 -> 500 HP PUMP, rental or standby per pump | C107: ='[4]6'!C6 -> DAY | D107: ='[4]6'!D6 -> 2000
A108: ='[4]6'!A7 -> MKN-1868 | B108: ='[4]6'!B7 -> 500 HP PUMP, 0 to 5,000 psi, operating, first 4 hours | C108: ='[4]6'!C7 -> 4 HRS | D108: ='[4]6'!D7 -> 4500
A109: ='[4]6'!A8 -> MKN-1869 | B109: ='[4]6'!B8 -> 500 HP PUMP, 0 to 5,000 psi, operating, additional hours | C109: ='[4]6'!C8 -> HOUR | D109: ='[4]6'!D8 -> 600
A110: ='[4]6'!A9 -> MKN-1870 | B110: ='[4]6'!B9 -> 500 HP PUMP, 5,001 to 10,000 psi, operating, first 4 hours | C110: ='[4]6'!C9 -> 4 HRS | D110: ='[4]6'!D9 -> 5225
A111: ='[4]6'!A10 -> MKN-1871 | B111: ='[4]6'!B10 -> 500 HP PUMP, 5,001 to 10,000 psi, operating, additional hours | C111: ='[4]6'!C10 -> HOUR | D111: ='[4]6'!D10 -> 1100
A113: 1,000 HP Pump
...

Sheet SOC Price List
A1: MAKAMAN LIBYA COMPANY For Sirte Oil Company
A2: Official Price List
A3: Prepared for Sirte Oil Company · All prices in Libyan Dinar (LYD), excluding VAT unless stated
A4: Client: | D4: Date:
A6: A. FISHING & SPECIAL TOOLS
F7: ← Contents
A8: Fishing Services — Supervisor & Transport
A9: Item Code | B9: Description | C9: Unit | D9: Price (LYD)
A10: ='[5]6'!A5 -> MKN 100-0205 | B10: ='[5]6'!B5 -> Fishing Tool Supervisor | C10: ='[5]6'!C5 -> LYD / Day | D10: ='[5]6'!D5 -> 5000
A11: ='[5]6'!A6 -> MKN 100-0210 | B11: ='[5]6'!B6 -> Tools pick up | C11: ='[5]6'!C6 -> km | D11: ='[5]6'!D6 -> 5
A12: ='[5]6'!A7 -> MKN 100-0215 | B12: ='[5]6'!B7 -> Truck | C12: ='[5]6'!C7 -> km | D12: ='[5]6'!D7 -> 7
A14: Baskets — Junk
A15: Item Code | B15: Description | C15: Unit | D15: First Day (LYD) | E15: Add. Day (LYD)
A16: ='[5]6'!A12 -> MKN 100-001 | B16: ='[5]6'!B12 -> Thru 3-3/4"OD | C16: ='[5]6'!C12 -> Per Day | D16: ='[5]6'!D12 -> 1150 | E16: ='[5]6'!E12 -> 210
A17: ='[5]6'!A13 -> MKN 100-002 | B17: ='[5]6'!B13 -> Thru 4-1/4"OD | C17: ='[5]6'!C13 -> Per Day | D17: ='[5]6'!D13 -> 1250 | E17: ='[5]6'!E13 -> 210
A18: ='[5]6'!A14 -> MKN 100-003 | B18: ='[5]6'!B14 -> Thru 4-3/4" OD | C18: ='[5]6'!C14 -> Per Day | D18: ='[5]6'!D14 -> 1250 | E18: ='[5]6'!E14 -> 210
A19: ='[5]6'!A15 -> MKN 100-004 | B19: ='[5]6'!B15 -> Thru 5-3/4" OD | C19: ='[5]6'!C15 -> Per Day | D19: ='[5]6'!D15 -> 1410 | E19: ='[5]6'!E15 -> 230
A20: ='[5]6'!A16 -> MKN 100-005 | B20: ='[5]6'!B16 -> Thru 6-1/8"OD | C20: ='[5]6'!C16 -> Per Day | D20: ='[5]6'!D16 -> 1410 | E20: ='[5]6'!E16 -> 230
A21: ='[5]6'!A17 -> MKN 100-006 | B21: ='[5]6'!B17 -> Thru 6-3/4"OD | C21: ='[5]6'!C17 -> Per Day | D21: ='[5]6'!D17 -> 1410 | E21: ='[5]6'!E17 -> 230
A22: ='[5]6'!A18 -> MKN 100-007 | B22: ='[5]6'!B18 -> Thru 7-3/4"OD | C22: ='[5]6'!C18 -> Per Day | D22: ='[5]6'!D18 -> 1520 | E22: ='[5]6'!E18 -> 245
A23: ='[5]6'!A19 -> MKN 100-008 | B23: ='[5]6'!B19 -> Thru 9-3/4"OD | C23: ='[5]6'!C19 -> Per Day | D23: ='[5]6'!D19 -> 1610 | E23: ='[5]6'!E19 -> 310
A24: ='[5]6'!A20 -> MKN 100-009 | B24: ='[5]6'!B20 -> Thru 10-3/4"OD | C24: ='[5]6'!C20 -> Per Day | D24: ='[5]6'!D20 -> 1610 | E24: ='[5]6'!E20 -> 310
A25: ='[5]6'!A21 -> MKN 100-011 | B25: ='[5]6'!B21 -> Thru 12-1/4"OD | C25: ='[5]6'!C21 -> Per Day | D25: ='[5]6'!D21 -> 1610 | E25: ='[5]6'!E21 -> 310
A27: Reverse Circulating Jet — Tungsten Carbide Dressed Head
A28: Item Code | B28: Description | C28: Unit | D28: Price (LYD)
A29: ='[5]6'!A25 -> MKN 100-012 | B29: ='[5]6'!B25 -> Thru 8-3/4"OD | C29: ='[5]6'!C25 -> Price/Largest OD in/Run | D29: ='[5]6'!D25 -> 650
A30: ='[5]6'!A26 -> MKN 100-013 | B30: ='[5]6'!B26 -> Thru 17-1/2"OD | C30: ='[5]6'!C26 -> Price/Largest OD in/Run | D30: ='[5]6'!D26 -> 750
A32: Baskets — Junk (Poor Boy, Drag Tooth or Friction Type)
A33: Item Code | B33: Description | C33: Unit | D33: Price (LYD)
A34: ='[5]6'!A28 -> MKN 100-014 | B34: ='[5]6'!B28 -> Thru 7" OD | C34: ='[5]6'!C28 -> Per Run | D34: ='[5]6'!D28 -> 1600
A35: ='[5]6'!A29 -> MKN 100-015 | B35: ='[5]6'!B29 -> Thru 10-3/4"OD | C35: ='[5]6'!C29 -> Per Run | D35: ='[5]6'!D29 -> 3050
A36: ='[5]6'!A30 -> MKN 100-016 | B36: ='[5]6'!B30 -> Thru 13-3/8"OD | C36: ='[5]6'!C30 -> Per Run | D36: ='[5]6'!D30 -> 4100
A38: Impression Blocks
A39: Item Code | B39: Description | C39: Unit | D39: Price (LYD)
A40: ='[5]6'!A34 -> MKN 100-017 | B40: ='[5]6'!B34 -> 8" OD & Smaller | C40: ='[5]6'!C34 -> HRS | D40: ='[5]6'!D34 -> 3800
A41: ='[5]6'!A35 -> MKN 100-018 | B41: ='[5]6'!B35 -> Over 8" | C41: ='[5]6'!C35 -> HRS | D41: ='[5]6'!D35 -> 4100
A43: Boxes — Metal
A44: Item Code | B44: Description | C44: Unit | D44: Price (LYD)
A45: ='[5]6'!A37 -> MKN 100-019 | B45: ='[5]6'!B37 -> ALL Sizes | C45: ='[5]6'!C37 -> Per Job | D45: ='[5]6'!D37 -> 305
A47: Triple Connection or Canfield — Washpipe Pin
A48: Item Code | B48: Description | C48: Unit | D48: First Day (LYD) | E48: Add. Day (LYD)
A49: ='[5]6'!A41 -> MKN100--020 | B49: ='[5]6'!B41 -> Thru 4 1/2" Washpipe Pin | C49: ='[5]6'!C41 -> LYD / Day | D49: ='[5]6'!D41 -> 800 | E49: ='[5]6'!E41 -> 420
A50: ='[5]6'!A42 -> MKN100--021 | B50: ='[5]6'!B42 -> Thru 5 3/4" Washpipe Pin | C50: ='[5]6'!C42 -> LYD / Day | D50: ='[5]6'!D42 -> 1050 | E50: ='[5]6'!E42 -> 500
A51: ='[5]6'!A43 -> MKN100--022 | B51: ='[5]6'!B43 -> Thru 8 3/8" Washpipe Pin | C51: ='[5]6'!C43 -> LYD / Day | D51: ='[5]6'!D43 -> 1200 | E51: ='[5]6'!E43 -> 610
A52: ='[5]6'!A44 -> MKN100--023 | B52: ='[5]6'!B44 -> Thru 10 3/4" Washpipe Pin | C52: ='[5]6'!C44 -> LYD / Day | D52: ='[5]6'!D44 -> 1310 | E52: ='[5]6'!E44 -> 710
A53: ='[5]6'!A45 -> MKN100--024 | B53: ='[5]6'!B45 -> Thru 13 3/8" Washpipe Pin | C53: ='[5]6'!C45 -> LYD / Day | D53: ='[5]6'!D45 -> 1700 | E53: ='[5]6'!E45 -> 870
A54: ='[5]6'!A46 -> MKN100--025 | B54: ='[5]6'!B46 -> Thru 16 1/2" Washpipe Pin | C54: ='[5]6'!C46 -> LYD / Day | D54: ='[5]6'!D46 -> 2050 | E54: ='[5]6'!E46 -> 1610
A55: ='[5]6'!A47 -> MKN100--026 | B55: ='[5]6'!B47 -> Thru 20" Washpipe Pin | C55: ='[5]6'!C47 -> LYD / Day | D55: ='[5]6'!D47 -> 2150 | E55: ='[5]6'!E47 -> 1710
A57: Safety or Control Bushing
A58: Item Code | B58: Description | C58: Unit | D58: Price (LYD)
A59: ='[5]6'!A51 -> MKN 100-027 | B59: ='[5]6'!B51 -> 7 5/8" OD & Smaller | C59: ='[5]6'!C51 -> Per Day | D59: ='[5]6'!D51 -> 905
A60: ='[5]6'!A52 -> MKN 100-028 | B60: ='[5]6'!B52 -> 9 5/8" OD & Smaller | C60: ='[5]6'!C52 -> Per Day | D60: ='[5]6'!D52 -> 1150
A61: ='[5]6'!A53 -> MKN 100-029 | B61: ='[5]6'!B53 -> 11 3/4" OD & Smaller | C61: ='[5]6'!C53 -> Per Day | D61: ='[5]6'!D53 -> 1320
A63: Clamp — Safety, Drill Collar or Wireline (Min. 4 Days)
A64: Item Code | B64: Description | C64: Unit | D64: First Day (LYD) | E64: Add. Day (LYD)
A65: ='[5]6'!A58 -> MKN 100-030 | B65: ='[5]6'!B58 -> Thru 10 segments | C65: ='[5]6'!C58 -> LYD / Day | D65: ='[5]6'!D58 -> 450 | E65: ='[5]6'!E58 -> 70
A66: ='[5]6'!A59 -> MKN 100-031 | B66: ='[5]6'!B59 -> Larger than 10 segments | C66: ='[5]6'!C59 -> LYD / Day | D66: ='[5]6'!D59 -> 650 | E66: ='[5]6'!E59 -> 120
A68: Cutter — Inside Casing, Mechanical
A69: Item Code | B69: Description | C69: Unit | D69: Price (LYD)
A70: ='[5]7'!A4 -> MKN 100-032 | B70: ='[5]7'!B4 -> Casing Thru 6-5/8" OD | C70: ='[5]7'!C4 -> PER CUT | D70: ='[5]7'!D4 -> 3900
A71: ='[5]7'!A5 -> MKN 100-033 | B71: ='[5]7'!B5 -> Casing Thru 8-5/8"OD | C71: ='[5]7'!C5 -> PER CUT | D71: ='[5]7'!D5 -> 4950
A73: Cutter — Outside, Casing / Drill / Tubing
A74: Item Code | B74: Description | C74: Unit | D74: Price (LYD)
A75: ='[5]7'!A7 -> MKN 100-034 | B75: ='[5]7'!B7 -> Mechanical cutter (Any size) | C75: ='[5]7'!C7 -> PER CUT | D75: ='[5]7'!D7 -> 6000
A76: ='[5]7'!A8 -> MKN 100-035 | B76: ='[5]7'!B8 -> Hydraulic or washover cutter (Any size) | C76: ='[5]7'!C8 -> PER CUT | D76: ='[5]7'!D8 -> 6100
A78: Cutter — Inside Casing, Hydraulic Pressure (Conventional Carbide)
A79: Item Code | B79: Description | C79: Unit | D79: Price (LYD)
A80: ='[5]7'!A12 -> MKN-100-36 | B80: ='[5]7'!B12 -> Thr u 9-5/8"OD OR Smaller | C80: ='[5]7'!C12 -> PER CUT | D80: ='[5]7'!D12 -> 5000
A81: ='[5]7'!A13 -> MKN-100-37 | B81: ='[5]7'!B13 -> Thr u 10-3/4"OD | C81: ='[5]7'!C13 -> PER CUT | D81: ='[5]7'!D13 -> 6100
A82: ='[5]7'!A14 -> MKN-100-38 | B82: ='[5]7'!B14 -> Thr u 13-3/8"OD | C82: ='[5]7'!C14 -> PER CUT | D82: ='[5]7'!D14 -> 7800
A83: ='[5]7'!A15 -> MKN-100-39 | B83: ='[5]7'!B15 -> Thr u 18"OD | C83: ='[5]7'!C15 -> PER CUT | D83: ='[5]7'!D15 -> 8150
A84: ='[5]7'!A16 -> MKN-100-40 | B84: ='[5]7'!B16 -> Thr u 26"OD | C84: ='[5]7'!C16 -> PER CUT | D84: ='[5]7'!D16 -> 11910
A85: ='[5]7'!A17 -> MKN-100-41 | B85: ='[5]7'!B17 -> Thr u 30"OD | C85: ='[5]7'!C17 -> PER CUT | D85: ='[5]7'!D17 -> 8120
A86: ='[5]7'!A18 -> MKN-100-42 | B86: ='[5]7'!B18 -> Thr u 36"OD | C86: ='[5]7'!C18 -> PER CUT | D86: ='[5]7'!D18 -> 9620
A87: ='[5]7'!A19 -> MKN-100-43 | B87: ='[5]7'!B19 -> Thr u 42"OD | C87: ='[5]7'!C19 -> PER CUT | D87: ='[5]7'!D19 -> 12870
A89: Drilling Jars — Fishing, Hydraulic or Mechanical Jar Intensifier (First 8 Hrs / Add. Hr)
A90: Item Code | B90: Description | C90: Unit | D90: First Day (LYD) | E90: Add. Day (LYD)
A91: ='[5]7'!A24 -> MKN-100-45 | B91: ='[5]7'!B24 -> Thru 6-1/2" OD | C91: ='[5]7'!C24 -> Per Day | D91: ='[5]7'!D24 -> 4050 | E91: ='[5]7'!E24 -> 2300
A92: ='[5]7'!A25 -> MKN-100-46 | B92: ='[5]7'!B25 -> Thru 8" OD | C92: ='[5]7'!C25 -> Per Day | D92: ='[5]7'!D25 -> 5110 | E92: ='[5]7'!E25 -> 3150
A94: Jars — Bumper Sub
A95: Item Code | B95: Description | C95: Unit | D95: First Day (LYD) | E95: Add. Day (LYD)
A96: ='[5]7'!A27 -> MKN-100-47 | B96: ='[5]7'!B27 -> Thru 4-1/4"OD | C96: ='[5]7'!C27 -> Per Day | D96: ='[5]7'!D27 -> 2150 | E96: ='[5]7'!E27 -> 1100
A97: ='[5]7'!A28 -> MKN-100-48 | B97: ='[5]7'!B28 -> Thru 6-1/4"OD | C97: ='[5]7'!C28 -> Per Day | D97: ='[5]7'!D28 -> 3000 | E97: ='[5]7'!E28 -> 1510
A99: Rotary Safety — Drill Pipe and Tubing
A100: Item Code | B100: Description | C100: Unit | D100: First Day (LYD) | E100: Add. Day (LYD)
A101: ='[5]7'!A33 -> MKN 100-049 | B101: ='[5]7'!B33 -> 3-1/2" conn. | C101: ='[5]7'!C33 -> Per Day | D101: ='[5]7'!D33 -> 610 | E101: ='[5]7'!E33 -> 400
A102: ='[5]7'!A34 -> MKN 100-050 | B102: ='[5]7'!B34 -> 6-5/8" conn. And smaller | C102: ='[5]7'!C34 -> Per Day | D102: ='[5]7'!D34 -> 790 | E102: ='[5]7'!E34 -> 570
A104: "J" Type Safety, Shear Pin Type or Unlatching
A105: Item Code | B105: Description | C105: Unit | D105: First Day (LYD) | E105: Add. Day (LYD)
A106: ='[5]7'!A36 -> MKN 100-051 | B106: ='[5]7'!B36 -> 6-5/8" conn. And smaller | C106: ='[5]7'!C36 -> Per Day | D106: ='[5]7'!D36 -> 1420 | E106: ='[5]7'!E36 -> 1250
A108: Magnets (Ditch)
A109: Item Code | B109: Description | C109: Unit | D109: First Day (LYD) | E109: Add. Day (LYD)
A110: ='[5]7'!A38 -> MFT 100-052 | B110: ='[5]7'!B38 -> All sizes | C110: ='[5]7'!C38 -> Per Day | D110: ='[5]7'!D38 -> 310 | E110: ='[5]7'!E38 -> 200
A112: Fishing Magnets
A113: Item Code | B113: Description | C113: Unit | D113: First Day (LYD) | E113: Add. Day (LYD)
A114: ='[5]7'!A40 -> MKN 100-053 | B114: ='[5]7'!B40 -> Thru 2-1/2"OD | C114: ='[5]7'!C40 -> Per Day | D114: ='[5]7'!D40 -> 480 | E114: ='[5]7'!E40 -> 390
A115: ='[5]7'!A41 -> MKN 100-054 | B115: ='[5]7'!B41 -> Thru 4-1/2"OD | C115: ='[5]7'!C41 -> Per Day | D115: ='[5]7'!D41 -> 780 | E115: ='[5]7'!E41 -> 600
A116: ='[5]7'!A42 -> MKN 100-055 | B116: ='[5]7'!B42 -> Thru 6-1/2"OD | C116: ='[5]7'!C42 -> Per Day | D116: ='[5]7'!D42 -> 1250 | E116: ='[5]7'!E42 -> 990
A117: ='[5]7'!A43 -> MKN 100-056 | B117: ='[5]7'!B43 -> Thru 8-1/2"OD | C117: ='[5]7'!C43 -> Per Day | D117: ='[5]7'!D43 -> 1450 | E117: ='[5]7'!E43 -> 1250
A118: ='[5]7'!A44 -> MKN 100-057 | B118: ='[5]7'!B44 -> Thru 11-1/2"OD | C118: ='[5]7'!C44 -> Per Day | D118: ='[5]7'!D44 -> 2050 | E118: ='[5]7'!E44 -> 1850
...

Sheet Zueitina Price List
A1: MAKAMAN LIBYA COMPANY For Zueitina Oil Company
A3: TRANSPORTATION & PERSONNEL
A4: Item Code | B4: Description | C4: Price
A5: MKN-0001 | B5: Pick-up with tools traveling to wells, per KM. | C5: 3.9
A6: MKN-0002 | B6: Tool operator, per day or fraction | C6: 950
A7: MKN-0003 | B7: Assistant Tool Operator, per day or fraction | C7: 800
A8: MKN-0004 | B8: Supervisor or Engineer, per day or fraction | C8: 1050
A9: MKN-0005 | B9: Helper, per day or fraction | C9: 500
A10: MKN-0006 | B10: STAND-BY FRIST SIX HOURS after arriving on location | C10: No charge
B11: After the Frist Six 06) Hours, STAND-BY, PER HOUR OR FRACTION until job started per tool, until PERSONNEL CHARGES will be in addition. | C11: 90
A12: MKN-0007 | B12: JOB CANCELITION When called to location and the job is not run, | C12: 1800
B13: due to circumstances beyond our control. PERSONNEL CHARGES are in addition.
A15: RETRIVEVABLE TEST, TREAT AND SQUEEZE PACKER.
A16: Price is determined by size and depth packer set. Time of job begins when tool starts in well and time end when recovered from well.
A17: FRIST-EIGHT (8) HOURS or Fraction
A19: Item Code | B19: Description | C19: Price
A20: MKN-0008 | B20: "Size thru 7 | C20: 2200
A21: MKN-0009 | B21: AFTER FIRST DAY size 7" | C21: 800
A22: MKN-0010 | B22: "Size thru 95/8. | C22: 2900
A23: MKN-0011 | B23: AFTER FIRST DAY size 9 5/8" | C23: 950
A24: MKN-0012 | B24: "Size 13 3/8. | C24: 5000
A25: MKN-0013 | B25: AFTER FIRST DAY size 13 3/8" | C25: 1100
A26: MKN-0014 | B26: All sizes, above 15,000 ft. per 100 ft. or fraction add | C26: 75
A27: MKN-0015 | B27: ADDITIONAL ZONE. Each ADDITIONAL ZONE on same run in well, any depth: | C27: 800
B28: (This change applies when tool is moved to another zone for any purpose.
B29: It does not include 'looking for casing leaks')
A30: MKN-0016 | B30: Unsuccessful run. | C30: 1100
A31: MKN-0017 | B31: Each Reset Packer For All Sizes | C31: 200
A34: RETRIEVABLE BRIDGE PLUG
A35: "RETRIEVABLE BRIDG PLUG (WHEN RUN SEPARATELY) PRICE IS DETERMINED BY SIZE AND DEPTHPACKER.SET. TIME OF JOB BEGINS WHEN TOOL STARTS IN WELL AND TIME END WHEN RECOVERED FROM WELL .FRIST-EIGHT (8) HOURS OR FRACTION"
A36: Item Code | B36: Description | C36: Price
A37: MKN-0018 | B37: Size thru 7" : first day | C37: 2200
A38: MKN-0019 | B38: Size thru 7" : after first day | C38: 850
A39: MKN-0020 | B39: Size thru 9 5/8" : first day | C39: 2900
A40: MKN-0021 | B40: Size thru 9 5/8" : after first day | C40: 950
A41: MKN-0022 | B41: Size 13 3/8" : first day | C41: 5000
A42: MKN-0023 | B42: Size 13 3/8" : after first day | C42: 1100
A43: MKN-0024 | B43: All sizes above 15,000 ft. per 100 ft. or fraction: add | C43: 75
A44: MKN-0025 | B44: ADDITIONAL TIME. Each additional consecutive 8-hour or fraction | C44: 1100
A45: MKN-0026 | B45: Frac sand (M.E.) 20–40 per pound | C45: 3.6
A46: MKN-0027 | B46: Unsuccessful run | C46: 1100
A48: RETRIEVABLE BRIDGE PLUG (When run with another MAKAMAN LIBYA CO. packer)
A49: Price is determined by size and depth packer set.
A50: Time of job begins when tool starts in well and time end when recovered from well.
A51: FIRST EIGHT (8) HOURS or Fraction
A53: Item Code | B53: Description | C53: Price
A54: MKN-0028 | B54: Size thru 7" : first day | C54: 1900
A55: MKN-0029 | B55: Size thru 7" : after first day | C55: 800
A56: MKN-0030 | B56: Size thru 9 5/8" : first day | C56: 2700
A57: MKN-0031 | B57: Size thru 9 5/8" : after first day | C57: 1000
A58: MKN-0032 | B58: Size 13 3/8" : first day | C58: 4500
A59: MKN-0033 | B59: Size 13 3/8" : after first day | C59: 1200
A60: MKN-0034 | B60: All sizes above 15,000 ft. per 100 ft. or fraction: add | C60: 70
A61: MKN-0035 | B61: ADDITIONAL TIME. Each additional consecutive 8-hour or fraction | C61: 800
A62: MKN-0036 | B62: Each reset on ADDITIONAL ZONE | C62: 700
A63: MKN-0037 | B63: Unsuccessful run | C63: 1300
A64: MKN-0038 | B64: Crossover subs, per sub, per job | C64: 50
A67: SETTING TOOLS & ACCESSORIES
A68: Item Code | B68: Description | C68: Price
A69: MKN-0039 | B69: MECHANICAL SETTING TOOL, per run | C69: 2500
A70: MKN-0040 | B70: Wire line kit for cement Retainer/Bridge plug, Per run | C70: 300
A71: MKN-0041 | B71: Tubing Stinger Coupling/ (SSA), Per job | C71: 600
A72: MKN-0042 | B72: Tubing Centralizer ,Per job | C72: 300
A74: DRILL CEMENT RETAINERS AND Drillable BRIDGE PLUG PACKER Per CSG OD
A75: Item Code | B75: Description | C75: Price
A76: MKN-0043 | B76: 4 1/2" | C76: 3500
A77: MKN-0044 | B77: 5" | C77: 3560
A78: MKN-0045 | B78: 5 1/2" | C78: 3560
A79: MKN-0046 | B79: 7" | C79: 3900
A80: MKN-0047 | B80: 9 5/8" | C80: 5200
A81: MKN-0048 | B81: 13 3/8" | C81: 8200
A84: STABILIZERS
A85: Item Code | B85: Description | C85: PER DAY | D85: Add. Day | E85: STAND BY RATE
A86: MKN-0049 | B86: STABILIZER Thru 6 1/8" | C86: 534 | D86: 200 | E86: 110
A87: MKN-0050 | B87: STABILIZER Thru 8 5/8" | C87: 607 | D87: 250 | E87: 122
A88: MKN-0051 | B88: STABILIZER Thru 12 1/4" | C88: 662 | D88: 300 | E88: 133
A89: MKN-0052 | B89: STABILIZER Thru 17 1/2" | C89: 772 | D89: 350 | E89: 166
A90: MKN-0053 | B90: HYDROLIC DRILLING JAR 4 3/4" OD & UNDER | C90: 1150 | D90: 900 | E90: 265
A91: MKN-0054 | B91: HYDROLIC DRILLING JAR THRU 5 3/4" OD | C91: 1600 | D91: 1000 | E91: 420
A92: MKN-0055 | B92: HYDROLIC DRILLING JAR THRU 6 1/4" OD | C92: 1800 | D92: 1200 | E92: 450
A93: MKN-0056 | B93: HYDROLIC DRILLING JAR THRU 7 3/4" OD | C93: 2000 | D93: 1300 | E93: 520
A94: MKN-0057 | B94: CASING SCRAPER 5" & 5 1/2" | C94: 400 | D94: 200 | E94: 120
A95: MKN-0058 | B95: CASING SCRAPER 7" | C95: 450 | D95: 220 | E95: 140
A96: MKN-0059 | B96: CASING SCRAPER 9 5/8" | C96: 550 | D96: 250 | E96: 160
A99: FILTRATION
A100: Item Code | B100: Description | C100: Unit | D100: Price
A101: MKN-0060 | B101: SERVICE SUPERVISOR FILTRATION UNIT | C101: PER DAY | D101: 1000
A102: MKN-0061 | B102: HELPER | C102: PER DAY | D102: 500
A103: MKN-0062 | B103: FILTRATION UNIT AND C-PUMP TRANSPORT | C103: PER DAY | D103: 400
A104: MKN-0063 | B104: FRAC TANK | C104: PER JOB | D104: 900
A105: MKN-0064 | B105: CENTER FUGAL PUMP | C105: PER JOB | D105: 900
A106: MKN-0065 | B106: FILTRATION UNIT | C106: PER DAY | D106: 300
A107: MKN-0066 | B107: FILTRATION CATRIDGES | C107: PER EACH | D107: 20
A110: PUMPING & STIMULATION SERVICES
B111: 400 HP PUMP
A112: Item Code | B112: Description | C112: Unit | D112: Price
A113: MKN-0067 | B113: 500 HP PUMP, rental or standby per pump | C113: DAY | D113: 2000
A114: MKN-0068 | B114: 500 HP PUMP, 0 to 5,000 psi, operating, first 4 hours | C114: 4 HRS | D114: 4500
A115: MKN-0069 | B115: 500 HP PUMP, 0 to 5,000 psi, operating, additional hours | C115: HOUR | D115: 600
A116: MKN-0070 | B116: 500 HP PUMP, 5,001 to 10,000 psi, operating, first 4 hours | C116: 4 HRS | D116: 5225
...
